{
    "checkpoint_times": [
        0.0009999275207519531,
        43.49300003051758,
        86.09599995613098,
        128.2409999370575
    ],
    "world_seed": 11248956,
    "frangel_config": {
        "max_time": 40.0,
        "try_to_simplify": false,
        "compare_programs_by_length": true,
        "verbose_level": 0,
        "generation": {
            "max_size": 40,
            "use_fragments_chance": 0.5,
            "use_entire_fragment_chance": 0.5,
            "use_angelic_conditions_chance": 0.2,
            "similar_new_extra_size": 8,
            "gen_similar_prob_new": 0.25
        },
        "angelic": {
            "max_time": 0.1,
            "boolean_expr_max_size": 6,
            "max_execute_attempts": 4,
            "max_allowed_fails": 0.75,
            "angelic_rulenode": null
        }
    },
    "frangel_seed": 1118,
    "solved": true,
    "used_fragments": [
        {
            "fragment": "1{2,3{5{8{13,22,26,28}18}}21}",
            "time": 27.703999996185303
        },
        {
            "fragment": "3{5{8{13,22,26,28}18}}",
            "time": 27.703999996185303
        },
        {
            "fragment": "5{8{13,22,26,28}18}",
            "time": 28.139999866485596
        },
        {
            "fragment": "21,",
            "time": 28.139999866485596
        },
        {
            "fragment": "1{2,3{5{8{13,22,26,28}18}}21}",
            "time": 30.141000032424927
        },
        {
            "fragment": "8{13,22,26,28}",
            "time": 30.182999849319458
        },
        {
            "fragment": "21,",
            "time": 30.182999849319458
        },
        {
            "fragment": "1{2,3{5{8{13,22,26,28}18}}21}",
            "time": 30.182999849319458
        },
        {
            "fragment": "1{2,3{5{8{13,22,26,28}18}}21}",
            "time": 30.203999996185303
        },
        {
            "fragment": "1{2,3{5{8{13,22,26,28}18}}21}",
            "time": 31.187999963760376
        },
        {
            "fragment": "2,",
            "time": 31.187999963760376
        },
        {
            "fragment": "3{5{8{11,22,26,28}18}}",
            "time": 31.187999963760376
        },
        {
            "fragment": "21,",
            "time": 31.187999963760376
        },
        {
            "fragment": "5{8{11,22,26,28}18}",
            "time": 33.13699984550476
        },
        {
            "fragment": "1{2,3{5{8{11,22,26,28}18}}21}",
            "time": 33.13699984550476
        },
        {
            "fragment": "3{5{8{13,22,26,28}18}}",
            "time": 33.19799995422363
        },
        {
            "fragment": "21,",
            "time": 33.19799995422363
        },
        {
            "fragment": "2,",
            "time": 33.19799995422363
        },
        {
            "fragment": "3{5{8{13,22,26,28}18}}",
            "time": 33.19799995422363
        },
        {
            "fragment": "21,",
            "time": 33.198999881744385
        },
        {
            "fragment": "2,",
            "time": 33.198999881744385
        },
        {
            "fragment": "3{5{8{13,22,26,28}18}}",
            "time": 33.198999881744385
        },
        {
            "fragment": "21,",
            "time": 33.198999881744385
        },
        {
            "fragment": "1{2,3{5{8{11,22,26,28}18}}21}",
            "time": 34.26199984550476
        },
        {
            "fragment": "2,",
            "time": 34.26199984550476
        },
        {
            "fragment": "11,",
            "time": 34.26199984550476
        },
        {
            "fragment": "22,",
            "time": 34.26199984550476
        },
        {
            "fragment": "26,",
            "time": 34.26199984550476
        },
        {
            "fragment": "1{2,3{5{8{13,22,26,28}18}}21}",
            "time": 34.26199984550476
        },
        {
            "fragment": "1{2,3{5{8{13,22,26,28}18}}21}",
            "time": 34.26199984550476
        },
        {
            "fragment": "3{5{8{13,22,26,28}18}}",
            "time": 34.26199984550476
        },
        {
            "fragment": "5{8{11,22,26,28}18}",
            "time": 34.26199984550476
        },
        {
            "fragment": "3{5{8{11,22,26,28}18}}",
            "time": 34.26199984550476
        },
        {
            "fragment": "1{2,3{5{8{11,22,26,28}18}}21}",
            "time": 34.26199984550476
        },
        {
            "fragment": "22,",
            "time": 34.26199984550476
        },
        {
            "fragment": "28,",
            "time": 34.26199984550476
        },
        {
            "fragment": "3{5{8{13,22,26,28}18}}",
            "time": 34.26199984550476
        },
        {
            "fragment": "21,",
            "time": 34.26199984550476
        },
        {
            "fragment": "1{2,3{5{8{11,22,26,28}18}}21}",
            "time": 34.26199984550476
        },
        {
            "fragment": "1{2,3{5{8{13,22,26,28}18}}21}",
            "time": 34.40599989891052
        },
        {
            "fragment": "1{2,3{5{8{11,22,26,28}18}}21}",
            "time": 35.08800005912781
        },
        {
            "fragment": "1{2,3{5{8{13,22,26,28}18}}21}",
            "time": 35.08800005912781
        },
        {
            "fragment": "1{2,3{5{8{11,22,26,28}18}}21}",
            "time": 35.08800005912781
        },
        {
            "fragment": "1{2,3{5{8{13,22,26,28}18}}21}",
            "time": 35.12999987602234
        },
        {
            "fragment": "1{2,3{5{8{11,22,26,28}18}}21}",
            "time": 38.55900001525879
        },
        {
            "fragment": "2,",
            "time": 53.39699983596802
        },
        {
            "fragment": "3{5{8{13,22,27,28}17}}",
            "time": 53.39699983596802
        },
        {
            "fragment": "21,",
            "time": 53.39699983596802
        },
        {
            "fragment": "1{2,3{5{8{13,22,27,28}17}}21}",
            "time": 53.39699983596802
        },
        {
            "fragment": "1{2,3{5{8{13,22,27,28}17}}21}",
            "time": 53.39699983596802
        },
        {
            "fragment": "3{5{8{13,22,27,28}17}}",
            "time": 53.39699983596802
        },
        {
            "fragment": "21,",
            "time": 53.39699983596802
        },
        {
            "fragment": "1{2,3{5{8{13,22,27,28}17}}21}",
            "time": 53.39699983596802
        },
        {
            "fragment": "8{13,22,27,28}",
            "time": 53.39699983596802
        },
        {
            "fragment": "21,",
            "time": 53.39699983596802
        },
        {
            "fragment": "1{2,3{5{8{13,22,27,28}17}}21}",
            "time": 53.50499987602234
        },
        {
            "fragment": "1{2,3{5{8{13,22,27,28}17}}21}",
            "time": 53.50499987602234
        },
        {
            "fragment": "3{5{8{13,22,27,28}17}}",
            "time": 53.58800005912781
        },
        {
            "fragment": "1{2,3{5{8{13,23,27,28}17}}21}",
            "time": 55.007999897003174
        },
        {
            "fragment": "1{2,3{5{8{13,23,27,28}17}}21}",
            "time": 55.11999988555908
        },
        {
            "fragment": "3{5{8{13,23,27,28}17}}",
            "time": 55.11999988555908
        },
        {
            "fragment": "21,",
            "time": 55.11999988555908
        },
        {
            "fragment": "1{2,3{5{8{13,23,27,28}17}}21}",
            "time": 55.11999988555908
        },
        {
            "fragment": "1{2,3{5{8{13,23,27,28}17}}21}",
            "time": 55.223999977111816
        },
        {
            "fragment": "1{2,3{5{8{13,23,27,28}17}}21}",
            "time": 55.223999977111816
        },
        {
            "fragment": "3{5{8{13,23,27,28}17}}",
            "time": 57.95099997520447
        },
        {
            "fragment": "21,",
            "time": 57.95099997520447
        },
        {
            "fragment": "2,",
            "time": 60.6729998588562
        },
        {
            "fragment": "3{5{8{13,23,27,28}17}}",
            "time": 60.6729998588562
        },
        {
            "fragment": "21,",
            "time": 60.6729998588562
        },
        {
            "fragment": "1{2,3{5{8{13,23,27,28}17}}21}",
            "time": 60.6729998588562
        },
        {
            "fragment": "2,",
            "time": 60.776000022888184
        },
        {
            "fragment": "3{5{8{13,23,27,28}17}}",
            "time": 60.776000022888184
        },
        {
            "fragment": "21,",
            "time": 60.776000022888184
        },
        {
            "fragment": "1{2,3{5{8{13,23,27,28}17}}21}",
            "time": 64.93099999427795
        },
        {
            "fragment": "1{2,3{5{8{13,23,27,28}17}}21}",
            "time": 64.93099999427795
        },
        {
            "fragment": "1{2,3{5{8{13,23,27,28}17}}21}",
            "time": 64.93099999427795
        },
        {
            "fragment": "2,",
            "time": 66.8420000076294
        },
        {
            "fragment": "3{5{8{13,23,27,28}17}}",
            "time": 66.8420000076294
        },
        {
            "fragment": "1{2,3{5{8{13,23,27,28}17}}21}",
            "time": 66.84299993515015
        },
        {
            "fragment": "1{2,3{5{8{13,23,27,28}17}}21}",
            "time": 66.84299993515015
        },
        {
            "fragment": "1{2,3{5{8{13,23,27,28}17}}21}",
            "time": 66.84299993515015
        },
        {
            "fragment": "1{2,3{5{8{13,23,27,28}17}}21}",
            "time": 66.84299993515015
        },
        {
            "fragment": "2,",
            "time": 66.84299993515015
        },
        {
            "fragment": "8{13,23,27,28}",
            "time": 66.84299993515015
        },
        {
            "fragment": "21,",
            "time": 66.84299993515015
        },
        {
            "fragment": "2,",
            "time": 66.84299993515015
        },
        {
            "fragment": "3{5{8{13,23,27,28}17}}",
            "time": 66.84299993515015
        },
        {
            "fragment": "13,",
            "time": 66.84299993515015
        },
        {
            "fragment": "28,",
            "time": 66.84299993515015
        },
        {
            "fragment": "21,",
            "time": 66.84299993515015
        },
        {
            "fragment": "1{2,3{5{8{13,23,27,28}17}}21}",
            "time": 66.88599991798401
        },
        {
            "fragment": "1{2,3{5{8{13,23,27,28}17}}21}",
            "time": 66.88599991798401
        },
        {
            "fragment": "2,",
            "time": 67.65899991989136
        },
        {
            "fragment": "5{8{13,23,27,28}17}",
            "time": 67.65899991989136
        },
        {
            "fragment": "5{8{13,23,27,28}17}",
            "time": 67.65899991989136
        },
        {
            "fragment": "1{2,3{5{8{13,23,27,28}17}}21}",
            "time": 69.41100001335144
        },
        {
            "fragment": "1{2,4{5{8{13,23,27,28}17}3{5{8{13,23,27,28}17}}}21}",
            "time": 69.41100001335144
        },
        {
            "fragment": "1{2,3{5{8{13,23,27,28}17}}21}",
            "time": 69.41100001335144
        },
        {
            "fragment": "1{2,3{5{8{13,23,27,28}17}}21}",
            "time": 72.13299989700317
        },
        {
            "fragment": "3{5{8{13,23,27,28}17}}",
            "time": 72.23300004005432
        },
        {
            "fragment": "2,",
            "time": 72.23300004005432
        },
        {
            "fragment": "3{5{8{13,23,27,28}17}}",
            "time": 72.23300004005432
        },
        {
            "fragment": "1{2,3{5{8{13,23,27,28}17}}21}",
            "time": 74.89199995994568
        },
        {
            "fragment": "5{8{13,23,27,28}17}",
            "time": 78.32299995422363
        },
        {
            "fragment": "21,",
            "time": 78.32299995422363
        },
        {
            "fragment": "5{8{13,23,27,28}17}",
            "time": 78.32299995422363
        },
        {
            "fragment": "1{2,4{5{8{13,23,27,28}17}3{5{8{13,23,27,28}17}}}21}",
            "time": 78.32399988174438
        },
        {
            "fragment": "1{2,4{5{8{13,23,27,28}17}3{5{8{13,23,27,28}17}}}21}",
            "time": 78.40400004386902
        },
        {
            "fragment": "1{2,4{5{8{13,23,27,28}17}3{5{8{13,23,27,28}17}}}21}",
            "time": 78.40400004386902
        },
        {
            "fragment": "2,",
            "time": 81.39299988746643
        },
        {
            "fragment": "5{8{13,23,27,28}17}",
            "time": 81.39299988746643
        },
        {
            "fragment": "21,",
            "time": 81.39299988746643
        },
        {
            "fragment": "1{2,3{5{8{13,23,27,28}17}}21}",
            "time": 81.39299988746643
        },
        {
            "fragment": "2,",
            "time": 82.59500002861023
        },
        {
            "fragment": "8{13,23,27,28}",
            "time": 82.59500002861023
        },
        {
            "fragment": "17,",
            "time": 82.59500002861023
        },
        {
            "fragment": "28,",
            "time": 82.59500002861023
        },
        {
            "fragment": "21,",
            "time": 82.59500002861023
        },
        {
            "fragment": "1{2,4{5{8{13,23,27,28}17}3{5{8{13,23,27,28}17}}}21}",
            "time": 82.68299984931946
        },
        {
            "fragment": "1{2,4{6{8{14,23,27,28}}3{5{8{13,25,27,29}17}}}21}",
            "time": 119.58999991416931
        },
        {
            "fragment": "1{2,4{6{8{14,23,27,28}}3{5{8{13,25,27,29}17}}}21}",
            "time": 120.71599984169006
        },
        {
            "fragment": "1{2,4{6{8{14,23,27,28}}3{5{8{13,25,27,29}17}}}21}",
            "time": 120.85800004005432
        },
        {
            "fragment": "1{2,4{6{8{14,23,27,28}}3{5{8{13,25,27,29}17}}}21}",
            "time": 120.85800004005432
        },
        {
            "fragment": "2,",
            "time": 120.85800004005432
        },
        {
            "fragment": "8{14,23,27,28}",
            "time": 120.85800004005432
        },
        {
            "fragment": "21,",
            "time": 120.85800004005432
        },
        {
            "fragment": "1{2,4{6{8{14,23,27,28}}3{5{8{13,25,27,29}17}}}21}",
            "time": 120.9229998588562
        },
        {
            "fragment": "2,",
            "time": 120.9229998588562
        },
        {
            "fragment": "8{13,25,27,29}",
            "time": 120.9229998588562
        },
        {
            "fragment": "6{8{14,23,27,28}}",
            "time": 120.9229998588562
        },
        {
            "fragment": "1{2,4{6{8{14,23,27,28}}3{5{8{13,25,27,29}17}}}21}",
            "time": 121.01999998092651
        },
        {
            "fragment": "1{2,4{6{8{14,23,27,28}}3{5{8{13,25,27,29}17}}}21}",
            "time": 121.08599996566772
        },
        {
            "fragment": "2,",
            "time": 121.36500000953674
        },
        {
            "fragment": "3{5{8{13,25,27,29}17}}",
            "time": 121.36500000953674
        },
        {
            "fragment": "21,",
            "time": 121.36500000953674
        },
        {
            "fragment": "2,",
            "time": 121.43899989128113
        },
        {
            "fragment": "17,",
            "time": 121.43899989128113
        },
        {
            "fragment": "8{13,25,27,29}",
            "time": 121.43899989128113
        },
        {
            "fragment": "21,",
            "time": 121.43899989128113
        },
        {
            "fragment": "1{2,4{6{8{14,23,27,28}}3{5{8{13,25,27,29}17}}}21}",
            "time": 121.52600002288818
        },
        {
            "fragment": "6{8{14,23,27,28}}",
            "time": 121.52600002288818
        },
        {
            "fragment": "1{2,4{6{8{14,23,27,28}}3{5{8{13,25,27,29}17}}}21}",
            "time": 121.58899998664856
        },
        {
            "fragment": "1{2,4{6{8{14,23,27,28}}3{5{8{13,25,27,29}17}}}21}",
            "time": 124.36899995803833
        },
        {
            "fragment": "2,",
            "time": 125.6579999923706
        },
        {
            "fragment": "6{8{14,23,27,28}}",
            "time": 125.6579999923706
        },
        {
            "fragment": "5{8{13,25,27,29}17}",
            "time": 125.6579999923706
        },
        {
            "fragment": "1{2,4{6{8{14,23,27,28}}3{5{8{13,25,27,29}17}}}21}",
            "time": 125.81200003623962
        },
        {
            "fragment": "2,",
            "time": 125.81200003623962
        },
        {
            "fragment": "8{13,25,27,29}",
            "time": 125.81200003623962
        },
        {
            "fragment": "1{2,3{5{8{15,22,27,28}17}}21}",
            "time": 136.73499989509583
        },
        {
            "fragment": "2,",
            "time": 136.73499989509583
        },
        {
            "fragment": "3{5{8{15,22,27,28}17}}",
            "time": 136.73499989509583
        },
        {
            "fragment": "3{5{8{15,22,27,28}17}}",
            "time": 138.65199995040894
        },
        {
            "fragment": "8{15,22,27,28}",
            "time": 138.65199995040894
        },
        {
            "fragment": "21,",
            "time": 138.65199995040894
        },
        {
            "fragment": "1{2,3{5{8{15,22,27,28}17}}21}",
            "time": 138.72499990463257
        },
        {
            "fragment": "2,",
            "time": 138.72499990463257
        },
        {
            "fragment": "8{15,22,27,28}",
            "time": 138.72499990463257
        },
        {
            "fragment": "1{2,3{5{8{15,22,27,28}17}}21}",
            "time": 138.77600002288818
        },
        {
            "fragment": "2,",
            "time": 138.88899993896484
        },
        {
            "fragment": "3{5{8{15,22,27,28}17}}",
            "time": 138.88899993896484
        },
        {
            "fragment": "21,",
            "time": 138.88899993896484
        },
        {
            "fragment": "2,",
            "time": 138.88899993896484
        },
        {
            "fragment": "3{5{8{15,22,27,28}17}}",
            "time": 138.88899993896484
        },
        {
            "fragment": "21,",
            "time": 138.88899993896484
        },
        {
            "fragment": "2,",
            "time": 138.93899989128113
        },
        {
            "fragment": "27,",
            "time": 138.93899989128113
        },
        {
            "fragment": "2,",
            "time": 139.00999999046326
        },
        {
            "fragment": "5{8{15,22,27,28}17}",
            "time": 139.00999999046326
        },
        {
            "fragment": "21,",
            "time": 139.00999999046326
        },
        {
            "fragment": "1{2,3{5{8{15,22,27,28}17}}21}",
            "time": 141.65100002288818
        },
        {
            "fragment": "1{2,3{5{8{15,22,27,28}17}}21}",
            "time": 141.72199988365173
        },
        {
            "fragment": "1{2,3{5{8{15,22,27,28}17}}21}",
            "time": 141.72199988365173
        },
        {
            "fragment": "5{8{15,22,27,28}17}",
            "time": 141.72199988365173
        },
        {
            "fragment": "21,",
            "time": 141.72199988365173
        },
        {
            "fragment": "3{5{8{15,25,27,28}17}}",
            "time": 143.01699995994568
        },
        {
            "fragment": "21,",
            "time": 143.01699995994568
        },
        {
            "fragment": "1{2,3{5{8{15,25,27,28}17}}21}",
            "time": 143.01699995994568
        },
        {
            "fragment": "1{2,3{5{8{15,25,27,28}17}}21}",
            "time": 143.125
        },
        {
            "fragment": "2,",
            "time": 143.20899987220764
        },
        {
            "fragment": "5{8{15,25,27,28}17}",
            "time": 143.20899987220764
        },
        {
            "fragment": "1{2,3{5{8{15,25,27,28}17}}21}",
            "time": 145.90599989891052
        },
        {
            "fragment": "1{2,3{5{8{15,25,27,28}17}}21}",
            "time": 145.97699999809265
        },
        {
            "fragment": "3{5{8{15,25,27,28}17}}",
            "time": 146.08699989318848
        },
        {
            "fragment": "1{2,3{5{8{15,25,27,28}17}}21}",
            "time": 146.14800000190735
        },
        {
            "fragment": "1{2,3{5{8{15,25,27,28}17}}21}",
            "time": 146.14800000190735
        },
        {
            "fragment": "1{2,3{5{8{15,25,27,28}17}}21}",
            "time": 146.14800000190735
        },
        {
            "fragment": "2,",
            "time": 146.14800000190735
        },
        {
            "fragment": "3{5{8{15,25,27,28}17}}",
            "time": 146.14800000190735
        },
        {
            "fragment": "1{2,3{5{8{15,25,27,28}17}}21}",
            "time": 147.39699983596802
        },
        {
            "fragment": "2,",
            "time": 147.49699997901917
        },
        {
            "fragment": "8{15,25,27,28}",
            "time": 147.49699997901917
        },
        {
            "fragment": "21,",
            "time": 147.49699997901917
        },
        {
            "fragment": "1{2,3{5{8{15,25,27,28}17}}21}",
            "time": 147.53799986839294
        },
        {
            "fragment": "1{2,3{5{8{15,25,27,28}17}}21}",
            "time": 151.60199999809265
        },
        {
            "fragment": "1{2,3{5{8{15,25,27,28}17}}21}",
            "time": 151.60199999809265
        },
        {
            "fragment": "2,",
            "time": 152.84099984169006
        },
        {
            "fragment": "3{5{8{15,25,26,28}17}}",
            "time": 152.84099984169006
        },
        {
            "fragment": "21,",
            "time": 152.84099984169006
        },
        {
            "fragment": "1{2,3{5{8{15,25,26,28}17}}21}",
            "time": 152.84099984169006
        },
        {
            "fragment": "1{2,3{5{8{15,25,26,28}17}}21}",
            "time": 154.09299993515015
        },
        {
            "fragment": "3{5{8{15,25,26,28}17}}",
            "time": 154.09299993515015
        },
        {
            "fragment": "21,",
            "time": 154.09299993515015
        },
        {
            "fragment": "5{8{15,25,26,28}17}",
            "time": 154.09299993515015
        },
        {
            "fragment": "21,",
            "time": 154.09299993515015
        },
        {
            "fragment": "1{2,3{5{8{15,25,26,28}17}}21}",
            "time": 155.47199988365173
        },
        {
            "fragment": "1{2,3{5{8{15,25,26,28}17}}21}",
            "time": 157.43700003623962
        },
        {
            "fragment": "2,",
            "time": 157.43700003623962
        },
        {
            "fragment": "3{5{8{15,25,26,28}17}}",
            "time": 157.43700003623962
        },
        {
            "fragment": "21,",
            "time": 157.43700003623962
        },
        {
            "fragment": "3{5{8{15,25,26,28}17}}",
            "time": 157.43700003623962
        },
        {
            "fragment": "5{8{15,25,26,28}17}",
            "time": 157.43700003623962
        },
        {
            "fragment": "2,",
            "time": 157.43700003623962
        },
        {
            "fragment": "8{15,25,26,28}",
            "time": 157.43700003623962
        },
        {
            "fragment": "1{2,3{5{8{15,25,26,28}17}}21}",
            "time": 157.5199999809265
        },
        {
            "fragment": "3{5{8{15,25,26,28}17}}",
            "time": 157.5199999809265
        },
        {
            "fragment": "2,",
            "time": 157.60399985313416
        },
        {
            "fragment": "3{5{8{15,25,26,28}17}}",
            "time": 157.60399985313416
        },
        {
            "fragment": "8{15,25,26,28}",
            "time": 157.65400004386902
        },
        {
            "fragment": "2,",
            "time": 157.73599982261658
        },
        {
            "fragment": "15,",
            "time": 157.73599982261658
        },
        {
            "fragment": "26,",
            "time": 157.73599982261658
        },
        {
            "fragment": "28,",
            "time": 157.73599982261658
        },
        {
            "fragment": "1{2,3{5{8{15,25,26,28}17}}21}",
            "time": 157.73599982261658
        }
    ],
    "experiment_description": "Fragments usage and modification probability - In this experiment, the probability of using fragments and the probability of modifiying fragments are changed.",
    "iterations": [
        {
            "final_grammar": "1: Program = begin\n    state = Init\n    Blocks\n    End\nend\n2: Init = mc_init(start_pos)\n3: Blocks = Block\n4: Blocks = begin\n    Block\n    Blocks\nend\n5: Block = while true\n    Move\n    Bool || break\nend\n6: Block = Move\n7: Block = if Bool\n    Move\nend\n8: Move = mc_move!(state, Direction, Times, Sprint, Jump)\n9: Direction = [\"forward\"]\n10: Direction = [\"back\"]\n11: Direction = [\"left\"]\n12: Direction = [\"right\"]\n13: Direction = [\"forward\", \"left\"]\n14: Direction = [\"forward\", \"right\"]\n15: Direction = [\"back\", \"left\"]\n16: Direction = [\"back\", \"right\"]\n17: Bool = mc_was_good_move(state)\n18: Bool = mc_has_moved(state)\n19: Bool = mc_is_done(state)\n20: Bool = !Bool\n21: End = mc_end(state)\n22: Times = 1\n23: Times = 2\n24: Times = 3\n25: Times = 4\n26: Sprint = true\n27: Sprint = false\n28: Jump = true\n29: Jump = false\n",
            "initial_position": [
                1.5,
                69.0,
                250.5
            ],
            "iterations": 97,
            "runtime": 43.49300003051758
        },
        {
            "final_grammar": "1: Program = begin\n    state = Init\n    Blocks\n    End\nend\n2: Init = mc_init(start_pos)\n3: Blocks = Block\n4: Blocks = begin\n    Block\n    Blocks\nend\n5: Block = while true\n    Move\n    Bool || break\nend\n6: Block = Move\n7: Block = if Bool\n    Move\nend\n8: Move = mc_move!(state, Direction, Times, Sprint, Jump)\n9: Direction = [\"forward\"]\n10: Direction = [\"back\"]\n11: Direction = [\"left\"]\n12: Direction = [\"right\"]\n13: Direction = [\"forward\", \"left\"]\n14: Direction = [\"forward\", \"right\"]\n15: Direction = [\"back\", \"left\"]\n16: Direction = [\"back\", \"right\"]\n17: Bool = mc_was_good_move(state)\n18: Bool = mc_has_moved(state)\n19: Bool = mc_is_done(state)\n20: Bool = !Bool\n21: End = mc_end(state)\n22: Times = 1\n23: Times = 2\n24: Times = 3\n25: Times = 4\n26: Sprint = true\n27: Sprint = false\n28: Jump = true\n29: Jump = false\n",
            "initial_position": [
                14.072796746510512,
                69.24918707874468,
                269.69999998807907
            ],
            "iterations": 65,
            "runtime": 42.60199999809265
        },
        {
            "final_grammar": "1: Program = begin\n    state = Init\n    Blocks\n    End\nend\n2: Init = mc_init(start_pos)\n3: Blocks = Block\n4: Blocks = begin\n    Block\n    Blocks\nend\n5: Block = while true\n    Move\n    Bool || break\nend\n6: Block = Move\n7: Block = if Bool\n    Move\nend\n8: Move = mc_move!(state, Direction, Times, Sprint, Jump)\n9: Direction = [\"forward\"]\n10: Direction = [\"back\"]\n11: Direction = [\"left\"]\n12: Direction = [\"right\"]\n13: Direction = [\"forward\", \"left\"]\n14: Direction = [\"forward\", \"right\"]\n15: Direction = [\"back\", \"left\"]\n16: Direction = [\"back\", \"right\"]\n17: Bool = mc_was_good_move(state)\n18: Bool = mc_has_moved(state)\n19: Bool = mc_is_done(state)\n20: Bool = !Bool\n21: End = mc_end(state)\n22: Times = 1\n23: Times = 2\n24: Times = 3\n25: Times = 4\n26: Sprint = true\n27: Sprint = false\n28: Jump = true\n29: Jump = false\n",
            "initial_position": [
                31.69999998807907,
                69.7531999805212,
                275.90785968954935
            ],
            "iterations": 81,
            "runtime": 42.144999980926514
        },
        {
            "final_grammar": "1: Program = begin\n    state = Init\n    Blocks\n    End\nend\n2: Init = mc_init(start_pos)\n3: Blocks = Block\n4: Blocks = begin\n    Block\n    Blocks\nend\n5: Block = while true\n    Move\n    Bool || break\nend\n6: Block = Move\n7: Block = if Bool\n    Move\nend\n8: Move = mc_move!(state, Direction, Times, Sprint, Jump)\n9: Direction = [\"forward\"]\n10: Direction = [\"back\"]\n11: Direction = [\"left\"]\n12: Direction = [\"right\"]\n13: Direction = [\"forward\", \"left\"]\n14: Direction = [\"forward\", \"right\"]\n15: Direction = [\"back\", \"left\"]\n16: Direction = [\"back\", \"right\"]\n17: Bool = mc_was_good_move(state)\n18: Bool = mc_has_moved(state)\n19: Bool = mc_is_done(state)\n20: Bool = !Bool\n21: End = mc_end(state)\n22: Times = 1\n23: Times = 2\n24: Times = 3\n25: Times = 4\n26: Sprint = true\n27: Sprint = false\n28: Jump = true\n29: Jump = false\n",
            "initial_position": [
                50.531968850192115,
                67.0,
                295.97603791356215
            ],
            "iterations": 66,
            "runtime": 30.62399983406067
        }
    ],
    "specification_config": {
        "max_reward": 74.0,
        "reward_percentages": [
            0.1,
            0.2,
            0.3,
            0.4,
            0.5,
            0.6,
            0.7,
            0.8,
            0.9
        ],
        "require_done": false
    },
    "world_description": "Big cave forward. Reward increases when entering cave. Goal not in cave.",
    "generated_programs": [
        {
            "time": 0.0009999275207519531,
            "program": "1{2,4{5{8{16,25,26,29}18}3{5{8{10,25,26,29}17}}}21}"
        },
        {
            "time": 0.6989998817443848,
            "program": "1{2,3{6{8{12,22,26,28}}}21}"
        },
        {
            "time": 0.7609999179840088,
            "program": "1{2,3{6{8{15,23,26,29}}}21}"
        },
        {
            "time": 0.8239998817443848,
            "program": "1{2,3{6{8{9,23,27,28}}}21}"
        },
        {
            "time": 0.8910000324249268,
            "program": "1{2,3{6{8{14,23,27,28}}}21}"
        },
        {
            "time": 0.9529998302459717,
            "program": "1{2,4{5{8{10,23,26,29}18}3{6{8{12,25,27,29}}}}21}"
        },
        {
            "time": 2.3569998741149902,
            "program": "1{2,3{6{8{9,24,26,29}}}21}"
        },
        {
            "time": 2.4759998321533203,
            "program": "1{2,3{6{8{11,22,27,28}}}21}"
        },
        {
            "time": 2.5279998779296875,
            "program": "1{2,3{6{8{10,22,26,28}}}21}"
        },
        {
            "time": 2.5820000171661377,
            "program": "1{2,3{5{8{15,22,27,28}18}}21}"
        },
        {
            "time": 3.567999839782715,
            "program": "1{2,4{6{8{14,23,27,28}}3{7{hole[Bool[0, 0, 0, 0, 0, 0, 0, 0, 0, 0, 0, 0, 0, 0, 0, 0, 1, 1, 1, 1, 0, 0, 0, 0, 0, 0, 0, 0, 0, 0, 1, 0, 0, 0, 0, 0, 0, 0, 0, 0, 0]],8{12,22,26,28}}}}21}"
        },
        {
            "time": 4.514999866485596,
            "program": "1{2,3{6{8{15,24,26,29}}}21}"
        },
        {
            "time": 4.588000059127808,
            "program": "1{2,3{7{18,8{15,25,26,28}}}21}"
        },
        {
            "time": 4.628999948501587,
            "program": "1{2,4{5{8{16,22,27,28}18}3{6{8{12,22,26,29}}}}21}"
        },
        {
            "time": 5.293999910354614,
            "program": "1{2,3{6{8{12,23,26,28}}}21}"
        },
        {
            "time": 5.365999937057495,
            "program": "1{2,3{6{8{12,22,26,29}}}21}"
        },
        {
            "time": 5.418999910354614,
            "program": "1{2,3{5{8{14,22,26,28}hole[Bool[0, 0, 0, 0, 0, 0, 0, 0, 0, 0, 0, 0, 0, 0, 0, 0, 1, 1, 1, 1, 0, 0, 0, 0, 0, 0, 0, 0, 0, 0, 1, 0, 0, 0, 0, 0, 0, 0, 0, 0, 0]]}}21}"
        },
        {
            "time": 7.3459999561309814,
            "program": "1{2,3{6{8{14,24,27,28}}}21}"
        },
        {
            "time": 7.415999889373779,
            "program": "1{2,4{6{8{13,22,27,28}}3{7{18,8{15,23,27,28}}}}21}"
        },
        {
            "time": 7.48799991607666,
            "program": "1{2,3{5{8{11,22,27,29}18}}21}"
        },
        {
            "time": 7.865999937057495,
            "program": "1{2,4{6{8{15,23,26,29}}3{6{8{9,22,27,29}}}}21}"
        },
        {
            "time": 7.937999963760376,
            "program": "1{2,3{5{8{9,22,27,29}17}}21}"
        },
        {
            "time": 8.652999877929688,
            "program": "1{2,4{7{17,8{15,23,26,28}}3{7{19,8{9,23,26,29}}}}21}"
        },
        {
            "time": 8.69599986076355,
            "program": "1{2,3{5{8{14,22,26,29}18}}21}"
        },
        {
            "time": 8.928999900817871,
            "program": "1{2,3{7{19,8{16,23,26,28}}}21}"
        },
        {
            "time": 8.968999862670898,
            "program": "1{2,4{7{19,8{16,25,27,29}}3{7{17,8{14,22,26,28}}}}21}"
        },
        {
            "time": 8.990999937057495,
            "program": "1{2,3{6{8{16,23,26,29}}}21}"
        },
        {
            "time": 9.031999826431274,
            "program": "1{2,3{7{19,8{12,22,27,28}}}21}"
        },
        {
            "time": 9.075000047683716,
            "program": "1{2,4{7{17,8{12,22,27,29}}3{6{8{13,22,27,28}}}}21}"
        },
        {
            "time": 9.105000019073486,
            "program": "1{2,3{7{hole[Bool[0, 0, 0, 0, 0, 0, 0, 0, 0, 0, 0, 0, 0, 0, 0, 0, 1, 1, 1, 1, 0, 0, 0, 0, 0, 0, 0, 0, 0, 0, 1, 0, 0, 0, 0, 0, 0, 0, 0, 0, 0]],8{9,23,26,29}}}21}"
        },
        {
            "time": 9.740999937057495,
            "program": "1{2,3{5{8{10,22,27,29}hole[Bool[0, 0, 0, 0, 0, 0, 0, 0, 0, 0, 0, 0, 0, 0, 0, 0, 1, 1, 1, 1, 0, 0, 0, 0, 0, 0, 0, 0, 0, 0, 1, 0, 0, 0, 0, 0, 0, 0, 0, 0, 0]]}}21}"
        },
        {
            "time": 11.6489999294281,
            "program": "1{2,3{6{8{11,22,26,28}}}21}"
        },
        {
            "time": 11.702999830245972,
            "program": "1{2,3{6{8{14,25,26,29}}}21}"
        },
        {
            "time": 11.78600001335144,
            "program": "1{2,3{7{19,8{15,23,27,29}}}21}"
        },
        {
            "time": 11.829999923706055,
            "program": "1{2,3{6{8{11,25,27,29}}}21}"
        },
        {
            "time": 11.894999980926514,
            "program": "1{2,3{6{8{11,23,27,29}}}21}"
        },
        {
            "time": 11.958999872207642,
            "program": "1{2,3{6{8{10,22,26,29}}}21}"
        },
        {
            "time": 12.008999824523926,
            "program": "1{2,4{5{8{15,22,27,29}19}4{6{8{14,24,27,29}}3{7{20{17}8{16,22,26,29}}}}}21}"
        },
        {
            "time": 12.098999977111816,
            "program": "1{2,4{6{8{16,25,27,28}}3{6{8{10,22,27,28}}}}21}"
        },
        {
            "time": 12.192999839782715,
            "program": "1{2,3{5{8{12,25,27,28}hole[Bool[0, 0, 0, 0, 0, 0, 0, 0, 0, 0, 0, 0, 0, 0, 0, 0, 1, 1, 1, 1, 0, 0, 0, 0, 0, 0, 0, 0, 0, 0, 1, 0, 0, 0, 0, 0, 0, 0, 0, 0, 0]]}}21}"
        },
        {
            "time": 16.25,
            "program": "1{2,4{6{8{13,25,27,29}}3{6{8{15,23,27,28}}}}21}"
        },
        {
            "time": 16.35699987411499,
            "program": "1{2,3{6{8{13,24,27,28}}}21}"
        },
        {
            "time": 16.431999921798706,
            "program": "1{2,3{5{8{15,25,27,29}19}}21}"
        },
        {
            "time": 16.516000032424927,
            "program": "1{2,3{6{8{13,24,26,29}}}21}"
        },
        {
            "time": 16.590999841690063,
            "program": "1{2,4{6{8{16,25,26,29}}3{5{8{13,24,26,29}hole[Bool[0, 0, 0, 0, 0, 0, 0, 0, 0, 0, 0, 0, 0, 0, 0, 0, 1, 1, 1, 1, 0, 0, 0, 0, 0, 0, 0, 0, 0, 0, 1, 0, 0, 0, 0, 0, 0, 0, 0, 0, 0]]}}}21}"
        },
        {
            "time": 21.22599983215332,
            "program": "1{2,3{7{19,8{12,24,27,28}}}21}"
        },
        {
            "time": 21.26799988746643,
            "program": "1{2,3{7{20{19}8{9,25,26,29}}}21}"
        },
        {
            "time": 21.329999923706055,
            "program": "1{2,3{6{8{13,22,26,28}}}21}"
        },
        {
            "time": 21.38699984550476,
            "program": "1{2,3{5{8{11,24,26,29}17}}21}"
        },
        {
            "time": 21.780999898910522,
            "program": "1{2,3{6{8{12,22,27,28}}}21}"
        },
        {
            "time": 21.83399987220764,
            "program": "1{2,3{7{17,8{12,23,26,28}}}21}"
        },
        {
            "time": 21.878000020980835,
            "program": "1{2,3{6{8{10,22,27,29}}}21}"
        },
        {
            "time": 21.91100001335144,
            "program": "1{2,3{6{8{13,25,27,28}}}21}"
        },
        {
            "time": 21.99899983406067,
            "program": "1{2,3{5{8{16,22,27,28}18}}21}"
        },
        {
            "time": 22.694999933242798,
            "program": "1{2,3{6{8{12,24,26,28}}}21}"
        },
        {
            "time": 22.77900004386902,
            "program": "1{2,3{6{8{10,22,27,28}}}21}"
        },
        {
            "time": 22.83299994468689,
            "program": "1{2,3{5{8{15,24,27,29}18}}21}"
        },
        {
            "time": 25.747999906539917,
            "program": "1{2,4{5{8{13,22,27,29}19}3{6{8{15,22,26,29}}}}21}"
        },
        {
            "time": 25.881999969482422,
            "program": "1{2,4{6{8{14,25,26,28}}3{6{8{12,22,26,28}}}}21}"
        },
        {
            "time": 25.97499990463257,
            "program": "1{2,3{7{hole[Bool[0, 0, 0, 0, 0, 0, 0, 0, 0, 0, 0, 0, 0, 0, 0, 0, 1, 1, 1, 1, 0, 0, 0, 0, 0, 0, 0, 0, 0, 0, 1, 0, 0, 0, 0, 0, 0, 0, 0, 0, 0]],8{13,24,27,28}}}21}"
        },
        {
            "time": 26.615000009536743,
            "program": "1{2,3{5{8{14,23,26,29}17}}21}"
        },
        {
            "time": 26.68400001525879,
            "program": "1{2,3{5{8{13,22,26,28}18}}21}"
        },
        {
            "time": 27.703999996185303,
            "program": "1{2,3{5{8{11,25,26,29}18}}21}"
        },
        {
            "time": 28.139999866485596,
            "program": "1{2,3{5{8{13,22,26,28}hole[Bool[0, 0, 0, 0, 0, 0, 0, 0, 0, 0, 0, 0, 0, 0, 0, 0, 1, 1, 1, 1, 0, 0, 0, 0, 0, 0, 0, 0, 0, 0, 1, 0, 0, 0, 0, 0, 0, 0, 0, 0, 0, 0, 0, 0, 0, 0, 0, 0, 0, 0, 0, 0]]}}21}"
        },
        {
            "time": 30.141000032424927,
            "program": "1{2,3{7{17,8{9,23,26,29}}}21}"
        },
        {
            "time": 30.182999849319458,
            "program": "1{2,3{7{17,8{9,22,27,28}}}21}"
        },
        {
            "time": 30.203999996185303,
            "program": "1{2,3{5{8{11,22,26,28}18}}21}"
        },
        {
            "time": 31.187999963760376,
            "program": "1{2,3{5{8{11,22,26,28}hole[Bool[0, 0, 0, 0, 0, 0, 0, 0, 0, 0, 0, 0, 0, 0, 0, 0, 1, 1, 1, 1, 0, 0, 0, 0, 0, 0, 0, 0, 0, 0, 1, 0, 0, 0, 0, 0, 0, 0, 0, 0, 0, 0, 0, 0, 0, 0, 0, 0, 0, 0, 0, 0, 0, 0, 0, 0, 0]]}}21}"
        },
        {
            "time": 33.13699984550476,
            "program": "1{2,4{6{8{10,23,26,29}}3{7{17,8{10,25,26,29}}}}21}"
        },
        {
            "time": 33.198999881744385,
            "program": "1{2,3{5{8{13,22,26,29}18}}21}"
        },
        {
            "time": 34.26199984550476,
            "program": "1{2,4{6{8{13,25,26,28}}3{6{8{12,24,27,28}}}}21}"
        },
        {
            "time": 34.406999826431274,
            "program": "1{2,3{7{hole[Bool[0, 0, 0, 0, 0, 0, 0, 0, 0, 0, 0, 0, 0, 0, 0, 0, 1, 1, 1, 1, 0, 0, 0, 0, 0, 0, 0, 0, 0, 0, 1, 0, 0, 0, 0, 0, 0, 0, 0, 0, 0, 0, 0, 0, 0, 0, 0, 0, 0, 0, 0, 0, 0, 0, 0, 0, 0]],8{14,24,26,28}}}21}"
        },
        {
            "time": 35.08800005912781,
            "program": "1{2,4{7{17,8{16,22,27,29}}3{7{18,8{16,24,27,28}}}}21}"
        },
        {
            "time": 35.12999987602234,
            "program": "1{2,3{5{8{13,24,26,28}hole[Bool[0, 0, 0, 0, 0, 0, 0, 0, 0, 0, 0, 0, 0, 0, 0, 0, 1, 1, 1, 1, 0, 0, 0, 0, 0, 0, 0, 0, 0, 0, 1, 0, 0, 0, 0, 0, 0, 0, 0, 0, 0, 0, 0, 0, 0, 0, 0, 0, 0, 0, 0, 0, 0, 0, 0, 0, 0]]}}21}"
        },
        {
            "time": 38.55900001525879,
            "program": "1{2,3{5{8{14,25,27,28}18}}21}"
        },
        {
            "time": 43.49300003051758,
            "program": "1{2,3{6{8{12,24,26,29}}}21}"
        },
        {
            "time": 43.57799983024597,
            "program": "1{2,4{5{8{12,23,27,29}hole[Bool[0, 0, 0, 0, 0, 0, 0, 0, 0, 0, 0, 0, 0, 0, 0, 0, 1, 1, 1, 1, 0, 0, 0, 0, 0, 0, 0, 0, 0, 0, 1, 0, 0, 0, 0, 0, 0, 0, 0, 0, 0]]}3{5{8{15,25,26,29}hole[Bool[0, 0, 0, 0, 0, 0, 0, 0, 0, 0, 0, 0, 0, 0, 0, 0, 1, 1, 1, 1, 0, 0, 0, 0, 0, 0, 0, 0, 0, 0, 1, 0, 0, 0, 0, 0, 0, 0, 0, 0, 0]]}}}21}"
        },
        {
            "time": 47.17199993133545,
            "program": "1{2,3{6{8{9,22,27,29}}}21}"
        },
        {
            "time": 47.22199988365173,
            "program": "1{2,3{7{17,8{15,24,26,28}}}21}"
        },
        {
            "time": 47.263999938964844,
            "program": "1{2,4{5{8{11,23,26,28}19}3{5{8{12,23,26,28}19}}}21}"
        },
        {
            "time": 47.34599995613098,
            "program": "1{2,3{6{8{14,25,27,28}}}21}"
        },
        {
            "time": 47.42999982833862,
            "program": "1{2,3{6{8{9,23,26,29}}}21}"
        },
        {
            "time": 47.49399995803833,
            "program": "1{2,3{7{17,8{10,24,27,29}}}21}"
        },
        {
            "time": 47.53600001335144,
            "program": "1{2,3{5{8{16,25,27,29}19}}21}"
        },
        {
            "time": 47.615999937057495,
            "program": "1{2,3{6{8{11,22,27,28}}}21}"
        },
        {
            "time": 47.66799998283386,
            "program": "1{2,3{6{8{12,24,27,29}}}21}"
        },
        {
            "time": 47.73799991607666,
            "program": "1{2,3{5{8{10,22,26,28}17}}21}"
        },
        {
            "time": 47.83099985122681,
            "program": "1{2,4{6{8{14,25,27,28}}3{5{8{11,24,27,29}hole[Bool[0, 0, 0, 0, 0, 0, 0, 0, 0, 0, 0, 0, 0, 0, 0, 0, 1, 1, 1, 1, 0, 0, 0, 0, 0, 0, 0, 0, 0, 0, 1, 0, 0, 0, 0, 0, 0, 0, 0, 0, 0]]}}}21}"
        },
        {
            "time": 52.35699987411499,
            "program": "1{2,3{6{8{11,24,26,28}}}21}"
        },
        {
            "time": 52.430999994277954,
            "program": "1{2,3{5{8{13,22,27,28}17}}21}"
        },
        {
            "time": 53.39699983596802,
            "program": "1{2,3{6{8{13,22,27,28}}}21}"
        },
        {
            "time": 53.50499987602234,
            "program": "1{2,3{5{8{14,24,26,29}20{18}}}21}"
        },
        {
            "time": 53.58800005912781,
            "program": "1{2,3{5{8{13,23,27,28}17}}21}"
        },
        {
            "time": 55.007999897003174,
            "program": "1{2,3{5{8{9,25,26,28}19}}21}"
        },
        {
            "time": 55.11999988555908,
            "program": "1{2,3{5{8{10,23,26,28}17}}21}"
        },
        {
            "time": 55.223999977111816,
            "program": "1{2,3{5{8{13,23,27,28}hole[Bool[0, 0, 0, 0, 0, 0, 0, 0, 0, 0, 0, 0, 0, 0, 0, 0, 1, 1, 1, 1, 0, 0, 0, 0, 0, 0, 0, 0, 0, 0, 1, 0, 0, 0, 0, 0, 0, 0, 0, 0, 0, 0, 0, 0, 0, 0, 0, 0, 0, 0, 0, 0]]}}21}"
        },
        {
            "time": 57.95099997520447,
            "program": "1{2,3{5{8{10,23,27,28}hole[Bool[0, 0, 0, 0, 0, 0, 0, 0, 0, 0, 0, 0, 0, 0, 0, 0, 1, 1, 1, 1, 0, 0, 0, 0, 0, 0, 0, 0, 0, 0, 1, 0, 0, 0, 0, 0, 0, 0, 0, 0, 0, 0, 0, 0, 0, 0, 0, 0, 0, 0, 0, 0]]}}21}"
        },
        {
            "time": 60.6729998588562,
            "program": "1{2,3{5{8{9,22,26,29}17}}21}"
        },
        {
            "time": 60.776000022888184,
            "program": "1{2,3{5{8{12,25,26,28}hole[Bool[0, 0, 0, 0, 0, 0, 0, 0, 0, 0, 0, 0, 0, 0, 0, 0, 1, 1, 1, 1, 0, 0, 0, 0, 0, 0, 0, 0, 0, 0, 1, 0, 0, 0, 0, 0, 0, 0, 0, 0, 0, 0, 0, 0, 0, 0, 0, 0, 0, 0, 0, 0]]}}21}"
        },
        {
            "time": 64.93099999427795,
            "program": "1{2,3{5{8{16,22,26,28}hole[Bool[0, 0, 0, 0, 0, 0, 0, 0, 0, 0, 0, 0, 0, 0, 0, 0, 1, 1, 1, 1, 0, 0, 0, 0, 0, 0, 0, 0, 0, 0, 1, 0, 0, 0, 0, 0, 0, 0, 0, 0, 0, 0, 0, 0, 0, 0, 0, 0, 0, 0, 0, 0]]}}21}"
        },
        {
            "time": 66.84299993515015,
            "program": "1{2,3{7{17,8{13,22,26,28}}}21}"
        },
        {
            "time": 66.88599991798401,
            "program": "1{2,3{5{8{16,24,26,29}20{19}}}21}"
        },
        {
            "time": 67.65899991989136,
            "program": "1{2,4{5{8{13,23,27,28}17}3{5{8{13,23,27,28}17}}}21}"
        },
        {
            "time": 69.41100001335144,
            "program": "1{2,3{5{8{12,23,26,28}hole[Bool[0, 0, 0, 0, 0, 0, 0, 0, 0, 0, 0, 0, 0, 0, 0, 0, 1, 1, 1, 1, 0, 0, 0, 0, 0, 0, 0, 0, 0, 0, 1, 0, 0, 0, 0, 0, 0, 0, 0, 0, 0, 0, 0, 0, 0, 0, 0, 0, 0, 0, 0, 0, 0, 0]]}}21}"
        },
        {
            "time": 72.13299989700317,
            "program": "1{2,4{6{8{16,22,26,28}}3{6{8{9,25,26,28}}}}21}"
        },
        {
            "time": 72.23300004005432,
            "program": "1{2,3{5{8{16,23,27,28}hole[Bool[0, 0, 0, 0, 0, 0, 0, 0, 0, 0, 0, 0, 0, 0, 0, 0, 1, 1, 1, 1, 0, 0, 0, 0, 0, 0, 0, 0, 0, 0, 1, 0, 0, 0, 0, 0, 0, 0, 0, 0, 0, 0, 0, 0, 0, 0, 0, 0, 0, 0, 0, 0, 0, 0]]}}21}"
        },
        {
            "time": 74.89199995994568,
            "program": "1{2,3{5{8{12,24,26,29}hole[Bool[0, 0, 0, 0, 0, 0, 0, 0, 0, 0, 0, 0, 0, 0, 0, 0, 1, 1, 1, 1, 0, 0, 0, 0, 0, 0, 0, 0, 0, 0, 1, 0, 0, 0, 0, 0, 0, 0, 0, 0, 0, 0, 0, 0, 0, 0, 0, 0, 0, 0, 0, 0, 0, 0]]}}21}"
        },
        {
            "time": 78.32399988174438,
            "program": "1{2,4{5{8{16,23,27,28}17}3{5{8{13,23,27,28}19}}}21}"
        },
        {
            "time": 78.40400004386902,
            "program": "1{2,4{5{8{13,23,26,28}hole[Bool[0, 0, 0, 0, 0, 0, 0, 0, 0, 0, 0, 0, 0, 0, 0, 0, 1, 1, 1, 1, 0, 0, 0, 0, 0, 0, 0, 0, 0, 0, 1, 0, 0, 0, 0, 0, 0, 0, 0, 0, 0, 0, 0, 0, 0, 0, 0, 0, 0, 0, 0, 0, 0, 0]]}3{6{8{13,22,27,28}}}}21}"
        },
        {
            "time": 81.39299988746643,
            "program": "1{2,3{5{8{13,23,26,28}17}}21}"
        },
        {
            "time": 82.59500002861023,
            "program": "1{2,4{5{8{13,23,27,28}20{17}}3{6{8{9,22,27,28}}}}21}"
        },
        {
            "time": 82.68299984931946,
            "program": "1{2,4{5{8{13,23,27,28}17}3{5{8{13,22,27,29}18}}}21}"
        },
        {
            "time": 86.09599995613098,
            "program": "1{2,4{5{8{15,23,26,29}20{19}}4{6{8{10,22,27,29}}3{6{8{11,24,27,29}}}}}21}"
        },
        {
            "time": 88.12399983406067,
            "program": "1{2,3{6{8{13,25,27,29}}}21}"
        },
        {
            "time": 88.2059998512268,
            "program": "1{2,4{5{8{12,23,26,28}19}3{6{8{14,23,26,28}}}}21}"
        },
        {
            "time": 88.28600001335144,
            "program": "1{2,3{6{8{9,25,27,29}}}21}"
        },
        {
            "time": 88.36800003051758,
            "program": "1{2,4{7{19,8{12,24,27,29}}3{6{8{13,22,26,28}}}}21}"
        },
        {
            "time": 88.41799998283386,
            "program": "1{2,4{6{8{9,24,26,28}}3{6{8{10,25,26,29}}}}21}"
        },
        {
            "time": 88.53199982643127,
            "program": "1{2,3{7{19,8{16,22,27,29}}}21}"
        },
        {
            "time": 88.57399988174438,
            "program": "1{2,3{7{17,8{12,25,26,28}}}21}"
        },
        {
            "time": 88.61399984359741,
            "program": "1{2,3{6{8{10,23,26,29}}}21}"
        },
        {
            "time": 88.67400002479553,
            "program": "1{2,4{7{17,8{11,24,26,29}}3{5{8{12,22,27,29}19}}}21}"
        },
        {
            "time": 88.72599983215332,
            "program": "1{2,4{5{8{11,22,26,28}hole[Bool[0, 0, 0, 0, 0, 0, 0, 0, 0, 0, 0, 0, 0, 0, 0, 0, 1, 1, 1, 1, 0, 0, 0, 0, 0, 0, 0, 0, 0, 0, 1, 0, 0, 0, 0, 0, 0, 0, 0, 0, 0]]}3{5{8{10,24,26,28}hole[Bool[0, 0, 0, 0, 0, 0, 0, 0, 0, 0, 0, 0, 0, 0, 0, 0, 1, 1, 1, 1, 0, 0, 0, 0, 0, 0, 0, 0, 0, 0, 1, 0, 0, 0, 0, 0, 0, 0, 0, 0, 0]]}}}21}"
        },
        {
            "time": 91.45899987220764,
            "program": "1{2,3{6{8{9,22,26,28}}}21}"
        },
        {
            "time": 91.50999999046326,
            "program": "1{2,3{6{8{12,24,27,29}}}21}"
        },
        {
            "time": 91.58599996566772,
            "program": "1{2,3{6{8{16,23,27,28}}}21}"
        },
        {
            "time": 91.64999985694885,
            "program": "1{2,3{5{8{13,25,27,28}17}}21}"
        },
        {
            "time": 91.74799990653992,
            "program": "1{2,3{6{8{10,22,26,29}}}21}"
        },
        {
            "time": 91.80200004577637,
            "program": "1{2,3{6{8{9,23,26,29}}}21}"
        },
        {
            "time": 91.86299991607666,
            "program": "1{2,3{6{8{9,22,26,29}}}21}"
        },
        {
            "time": 91.91499996185303,
            "program": "1{2,3{7{19,8{9,23,27,28}}}21}"
        },
        {
            "time": 91.95700001716614,
            "program": "1{2,3{7{18,8{9,25,27,29}}}21}"
        },
        {
            "time": 91.99799990653992,
            "program": "1{2,3{6{8{16,24,26,29}}}21}"
        },
        {
            "time": 92.07099986076355,
            "program": "1{2,3{5{8{11,24,27,29}hole[Bool[0, 0, 0, 0, 0, 0, 0, 0, 0, 0, 0, 0, 0, 0, 0, 0, 1, 1, 1, 1, 0, 0, 0, 0, 0, 0, 0, 0, 0, 0, 1, 0, 0, 0, 0, 0, 0, 0, 0, 0, 0]]}}21}"
        },
        {
            "time": 95.47099995613098,
            "program": "1{2,3{7{20{19}8{10,23,27,28}}}21}"
        },
        {
            "time": 95.53399991989136,
            "program": "1{2,3{5{8{12,23,26,29}18}}21}"
        },
        {
            "time": 95.72399997711182,
            "program": "1{2,3{5{8{11,23,26,28}17}}21}"
        },
        {
            "time": 95.80999994277954,
            "program": "1{2,3{6{8{10,25,27,28}}}21}"
        },
        {
            "time": 95.87299990653992,
            "program": "1{2,3{6{8{12,25,26,29}}}21}"
        },
        {
            "time": 95.95299983024597,
            "program": "1{2,3{6{8{9,25,26,29}}}21}"
        },
        {
            "time": 96.03399991989136,
            "program": "1{2,3{5{8{16,23,26,29}hole[Bool[0, 0, 0, 0, 0, 0, 0, 0, 0, 0, 0, 0, 0, 0, 0, 0, 1, 1, 1, 1, 0, 0, 0, 0, 0, 0, 0, 0, 0, 0, 1, 0, 0, 0, 0, 0, 0, 0, 0, 0, 0]]}}21}"
        },
        {
            "time": 98.67599987983704,
            "program": "1{2,4{5{8{12,23,26,28}hole[Bool[0, 0, 0, 0, 0, 0, 0, 0, 0, 0, 0, 0, 0, 0, 0, 0, 1, 1, 1, 1, 0, 0, 0, 0, 0, 0, 0, 0, 0, 0, 1, 0, 0, 0, 0, 0, 0, 0, 0, 0, 0]]}3{6{8{10,23,26,29}}}}21}"
        },
        {
            "time": 101.88299989700317,
            "program": "1{2,3{6{8{13,22,26,28}}}21}"
        },
        {
            "time": 101.93700003623962,
            "program": "1{2,4{7{17,8{15,22,27,29}}3{5{8{13,25,26,29}18}}}21}"
        },
        {
            "time": 104.22099995613098,
            "program": "1{2,4{7{17,8{11,23,26,29}}3{7{20{17}8{10,22,26,29}}}}21}"
        },
        {
            "time": 104.36299991607666,
            "program": "1{2,3{7{hole[Bool[0, 0, 0, 0, 0, 0, 0, 0, 0, 0, 0, 0, 0, 0, 0, 0, 1, 1, 1, 1, 0, 0, 0, 0, 0, 0, 0, 0, 0, 0, 1, 0, 0, 0, 0, 0, 0, 0, 0, 0, 0]],8{14,24,26,28}}}21}"
        },
        {
            "time": 105.23199987411499,
            "program": "1{2,3{7{hole[Bool[0, 0, 0, 0, 0, 0, 0, 0, 0, 0, 0, 0, 0, 0, 0, 0, 1, 1, 1, 1, 0, 0, 0, 0, 0, 0, 0, 0, 0, 0, 1, 0, 0, 0, 0, 0, 0, 0, 0, 0, 0]],8{14,23,26,28}}}21}"
        },
        {
            "time": 106.02600002288818,
            "program": "1{2,3{6{8{16,22,27,29}}}21}"
        },
        {
            "time": 106.07999992370605,
            "program": "1{2,4{5{8{16,25,26,29}hole[Bool[0, 0, 0, 0, 0, 0, 0, 0, 0, 0, 0, 0, 0, 0, 0, 0, 1, 1, 1, 1, 0, 0, 0, 0, 0, 0, 0, 0, 0, 0, 1, 0, 0, 0, 0, 0, 0, 0, 0, 0, 0]]}3{5{8{9,23,27,29}hole[Bool[0, 0, 0, 0, 0, 0, 0, 0, 0, 0, 0, 0, 0, 0, 0, 0, 1, 1, 1, 1, 0, 0, 0, 0, 0, 0, 0, 0, 0, 0, 1, 0, 0, 0, 0, 0, 0, 0, 0, 0, 0]]}}}21}"
        },
        {
            "time": 110.15199995040894,
            "program": "1{2,4{5{8{13,24,27,29}19}3{5{8{10,22,27,29}18}}}21}"
        },
        {
            "time": 110.40199995040894,
            "program": "1{2,3{7{hole[Bool[0, 0, 0, 0, 0, 0, 0, 0, 0, 0, 0, 0, 0, 0, 0, 0, 1, 1, 1, 1, 0, 0, 0, 0, 0, 0, 0, 0, 0, 0, 1, 0, 0, 0, 0, 0, 0, 0, 0, 0, 0]],8{13,23,27,29}}}21}"
        },
        {
            "time": 111.13399982452393,
            "program": "1{2,4{6{8{9,24,26,28}}3{5{8{12,25,27,29}19}}}21}"
        },
        {
            "time": 111.25499987602234,
            "program": "1{2,4{7{17,8{13,23,27,29}}3{6{8{15,22,27,28}}}}21}"
        },
        {
            "time": 111.30799984931946,
            "program": "1{2,3{6{8{11,25,26,28}}}21}"
        },
        {
            "time": 111.3899998664856,
            "program": "1{2,3{5{8{10,23,27,28}18}}21}"
        },
        {
            "time": 113.34299993515015,
            "program": "1{2,3{6{8{14,25,27,28}}}21}"
        },
        {
            "time": 113.4689998626709,
            "program": "1{2,3{5{8{9,23,26,28}17}}21}"
        },
        {
            "time": 113.57099986076355,
            "program": "1{2,3{7{20{17}8{9,24,27,29}}}21}"
        },
        {
            "time": 113.64499998092651,
            "program": "1{2,3{5{8{14,24,26,29}19}}21}"
        },
        {
            "time": 113.7189998626709,
            "program": "1{2,3{6{8{16,22,26,29}}}21}"
        },
        {
            "time": 113.77300000190735,
            "program": "1{2,3{6{8{16,25,27,28}}}21}"
        },
        {
            "time": 113.85800004005432,
            "program": "1{2,3{6{8{16,23,27,29}}}21}"
        },
        {
            "time": 113.9210000038147,
            "program": "1{2,3{7{17,8{14,23,27,29}}}21}"
        },
        {
            "time": 113.96300005912781,
            "program": "1{2,4{5{8{15,24,26,28}20{20{17}}}3{5{8{11,24,27,29}20{19}}}}21}"
        },
        {
            "time": 116.9210000038147,
            "program": "1{2,3{7{17,8{16,24,26,28}}}21}"
        },
        {
            "time": 116.96300005912781,
            "program": "1{2,3{7{17,8{16,24,27,29}}}21}"
        },
        {
            "time": 117.00399994850159,
            "program": "1{2,3{6{8{10,25,26,28}}}21}"
        },
        {
            "time": 117.08699989318848,
            "program": "1{2,4{5{8{9,24,26,29}19}3{6{8{13,24,26,28}}}}21}"
        },
        {
            "time": 117.18899989128113,
            "program": "1{2,3{7{hole[Bool[0, 0, 0, 0, 0, 0, 0, 0, 0, 0, 0, 0, 0, 0, 0, 0, 1, 1, 1, 1, 0, 0, 0, 0, 0, 0, 0, 0, 0, 0, 1, 0, 0, 0, 0, 0, 0, 0, 0, 0, 0]],8{11,25,27,28}}}21}"
        },
        {
            "time": 117.94700002670288,
            "program": "1{2,3{6{8{16,24,27,29}}}21}"
        },
        {
            "time": 118.00099992752075,
            "program": "1{2,3{6{8{13,24,27,28}}}21}"
        },
        {
            "time": 118.07399988174438,
            "program": "1{2,4{6{8{14,23,27,28}}3{5{8{13,25,27,29}17}}}21}"
        },
        {
            "time": 119.58999991416931,
            "program": "1{2,4{6{8{14,23,27,28}}3{5{8{13,22,27,29}17}}}21}"
        },
        {
            "time": 120.71599984169006,
            "program": "1{2,4{6{8{11,22,27,29}}3{5{8{11,25,27,29}18}}}21}"
        },
        {
            "time": 120.85800004005432,
            "program": "1{2,3{5{8{14,23,27,28}19}}21}"
        },
        {
            "time": 120.9229998588562,
            "program": "1{2,4{6{8{13,22,27,29}}3{6{8{12,24,27,28}}}}21}"
        },
        {
            "time": 121.01999998092651,
            "program": "1{2,4{6{8{12,22,27,28}}3{5{8{13,22,27,28}19}}}21}"
        },
        {
            "time": 121.08599996566772,
            "program": "1{2,4{6{8{14,25,27,28}}3{5{8{12,23,26,29}18}}}21}"
        },
        {
            "time": 121.36500000953674,
            "program": "1{2,3{5{8{16,24,27,28}17}}21}"
        },
        {
            "time": 121.43899989128113,
            "program": "1{2,3{7{20{17}8{13,25,27,29}}}21}"
        },
        {
            "time": 121.52600002288818,
            "program": "1{2,3{6{8{14,23,27,28}}}21}"
        },
        {
            "time": 121.58899998664856,
            "program": "1{2,4{6{8{16,24,27,29}}3{5{8{10,22,26,28}hole[Bool[0, 0, 0, 0, 0, 0, 0, 0, 0, 0, 0, 0, 0, 0, 0, 0, 1, 1, 1, 1, 0, 0, 0, 0, 0, 0, 0, 0, 0, 0, 1, 0, 0, 0, 0, 0, 0, 0, 0, 0, 0, 0, 0, 0, 0, 0, 0, 0, 0, 0, 0, 0, 0, 0, 0, 0, 0, 0]]}}}21}"
        },
        {
            "time": 124.36899995803833,
            "program": "1{2,4{6{8{9,24,27,28}}3{5{8{13,25,26,29}20{20{17}}}}}21}"
        },
        {
            "time": 125.6579999923706,
            "program": "1{2,3{5{8{10,25,27,29}17}}21}"
        },
        {
            "time": 125.81200003623962,
            "program": "1{2,3{7{hole[Bool[0, 0, 0, 0, 0, 0, 0, 0, 0, 0, 0, 0, 0, 0, 0, 0, 1, 1, 1, 1, 0, 0, 0, 0, 0, 0, 0, 0, 0, 0, 1, 0, 0, 0, 0, 0, 0, 0, 0, 0, 0, 0, 0, 0, 0, 0, 0, 0, 0, 0, 0, 0, 0, 0, 0, 0, 0, 0]],8{13,25,27,29}}}21}"
        },
        {
            "time": 128.2409999370575,
            "program": "1{2,3{7{19,8{12,25,26,28}}}21}"
        },
        {
            "time": 128.28099989891052,
            "program": "1{2,4{6{8{9,22,27,29}}3{6{8{16,23,26,29}}}}21}"
        },
        {
            "time": 128.3309998512268,
            "program": "1{2,3{6{8{13,22,27,29}}}21}"
        },
        {
            "time": 128.38100004196167,
            "program": "1{2,3{6{8{10,23,26,28}}}21}"
        },
        {
            "time": 128.44299983978271,
            "program": "1{2,3{7{19,8{10,23,26,28}}}21}"
        },
        {
            "time": 128.48499989509583,
            "program": "1{2,3{5{8{11,23,27,29}18}}21}"
        },
        {
            "time": 130.47199988365173,
            "program": "1{2,3{6{8{9,24,26,28}}}21}"
        },
        {
            "time": 130.58599996566772,
            "program": "1{2,3{5{8{14,22,27,28}17}}21}"
        },
        {
            "time": 130.6380000114441,
            "program": "1{2,3{7{18,8{13,25,27,29}}}21}"
        },
        {
            "time": 130.67899990081787,
            "program": "1{2,3{6{8{13,25,26,28}}}21}"
        },
        {
            "time": 130.7389998435974,
            "program": "1{2,4{6{8{10,25,27,29}}3{6{8{9,23,27,29}}}}21}"
        },
        {
            "time": 130.8420000076294,
            "program": "1{2,3{6{8{10,24,27,28}}}21}"
        },
        {
            "time": 130.91299986839294,
            "program": "1{2,3{6{8{14,24,26,29}}}21}"
        },
        {
            "time": 130.98399996757507,
            "program": "1{2,3{5{8{13,22,27,28}hole[Bool[0, 0, 0, 0, 0, 0, 0, 0, 0, 0, 0, 0, 0, 0, 0, 0, 1, 1, 1, 1, 0, 0, 0, 0, 0, 0, 0, 0, 0, 0, 1, 0, 0, 0, 0, 0, 0, 0, 0, 0, 0]]}}21}"
        },
        {
            "time": 132.9079999923706,
            "program": "1{2,3{6{8{16,23,26,29}}}21}"
        },
        {
            "time": 132.97000002861023,
            "program": "1{2,3{6{8{9,23,26,28}}}21}"
        },
        {
            "time": 133.03199982643127,
            "program": "1{2,3{5{8{13,23,26,29}hole[Bool[0, 0, 0, 0, 0, 0, 0, 0, 0, 0, 0, 0, 0, 0, 0, 0, 1, 1, 1, 1, 0, 0, 0, 0, 0, 0, 0, 0, 0, 0, 1, 0, 0, 0, 0, 0, 0, 0, 0, 0, 0]]}}21}"
        },
        {
            "time": 135.74899983406067,
            "program": "1{2,3{5{8{15,22,27,28}17}}21}"
        },
        {
            "time": 136.73499989509583,
            "program": "1{2,3{5{8{15,22,27,28}hole[Bool[0, 0, 0, 0, 0, 0, 0, 0, 0, 0, 0, 0, 0, 0, 0, 0, 1, 1, 1, 1, 0, 0, 0, 0, 0, 0, 0, 0, 0, 0, 1, 0, 0, 0, 0, 0, 0, 0, 0, 0, 0, 0, 0, 0, 0, 0, 0, 0, 0, 0, 0, 0]]}}21}"
        },
        {
            "time": 138.65199995040894,
            "program": "1{2,3{6{8{9,24,27,28}}}21}"
        },
        {
            "time": 138.72499990463257,
            "program": "1{2,3{6{8{14,22,27,28}}}21}"
        },
        {
            "time": 138.77600002288818,
            "program": "1{2,4{7{20{18}8{12,25,27,29}}3{7{18,8{12,24,26,28}}}}21}"
        },
        {
            "time": 138.88899993896484,
            "program": "1{2,3{5{8{16,22,26,28}17}}21}"
        },
        {
            "time": 138.93899989128113,
            "program": "1{2,3{6{8{12,24,27,29}}}21}"
        },
        {
            "time": 139.00999999046326,
            "program": "1{2,3{5{8{10,23,27,28}hole[Bool[0, 0, 0, 0, 0, 0, 0, 0, 0, 0, 0, 0, 0, 0, 0, 0, 1, 1, 1, 1, 0, 0, 0, 0, 0, 0, 0, 0, 0, 0, 1, 0, 0, 0, 0, 0, 0, 0, 0, 0, 0, 0, 0, 0, 0, 0, 0, 0, 0, 0, 0, 0]]}}21}"
        },
        {
            "time": 141.65100002288818,
            "program": "1{2,3{6{8{16,24,27,28}}}21}"
        },
        {
            "time": 141.72199988365173,
            "program": "1{2,3{5{8{15,25,27,28}17}}21}"
        },
        {
            "time": 143.01699995994568,
            "program": "1{2,3{5{8{14,24,26,29}17}}21}"
        },
        {
            "time": 143.12599992752075,
            "program": "1{2,3{6{8{14,25,26,28}}}21}"
        },
        {
            "time": 143.21000003814697,
            "program": "1{2,3{5{8{12,23,26,29}hole[Bool[0, 0, 0, 0, 0, 0, 0, 0, 0, 0, 0, 0, 0, 0, 0, 0, 1, 1, 1, 1, 0, 0, 0, 0, 0, 0, 0, 0, 0, 0, 1, 0, 0, 0, 0, 0, 0, 0, 0, 0, 0, 0, 0, 0, 0, 0, 0, 0, 0, 0, 0, 0]]}}21}"
        },
        {
            "time": 145.90599989891052,
            "program": "1{2,4{6{8{12,23,26,28}}3{6{8{12,22,27,29}}}}21}"
        },
        {
            "time": 145.97699999809265,
            "program": "1{2,4{6{8{10,25,26,29}}3{6{8{14,24,27,28}}}}21}"
        },
        {
            "time": 146.08699989318848,
            "program": "1{2,3{5{8{9,23,26,28}17}}21}"
        },
        {
            "time": 146.14800000190735,
            "program": "1{2,3{5{8{15,24,27,28}17}}21}"
        },
        {
            "time": 147.39699983596802,
            "program": "1{2,4{6{8{13,23,26,28}}3{7{20{18}8{14,25,27,28}}}}21}"
        },
        {
            "time": 147.49699997901917,
            "program": "1{2,3{7{17,8{15,25,27,28}}}21}"
        },
        {
            "time": 147.53799986839294,
            "program": "1{2,3{5{8{15,25,27,28}hole[Bool[0, 0, 0, 0, 0, 0, 0, 0, 0, 0, 0, 0, 0, 0, 0, 0, 1, 1, 1, 1, 0, 0, 0, 0, 0, 0, 0, 0, 0, 0, 1, 0, 0, 0, 0, 0, 0, 0, 0, 0, 0, 0, 0, 0, 0, 0, 0, 0, 0, 0, 0, 0]]}}21}"
        },
        {
            "time": 151.60199999809265,
            "program": "1{2,3{5{8{15,25,26,28}17}}21}"
        },
        {
            "time": 152.84099984169006,
            "program": "1{2,3{5{8{15,23,26,28}17}}21}"
        },
        {
            "time": 154.09299993515015,
            "program": "1{2,4{5{8{15,25,26,28}17}3{6{8{13,25,26,29}}}}21}"
        },
        {
            "time": 155.47199988365173,
            "program": "1{2,3{5{8{12,22,26,29}hole[Bool[0, 0, 0, 0, 0, 0, 0, 0, 0, 0, 0, 0, 0, 0, 0, 0, 1, 1, 1, 1, 0, 0, 0, 0, 0, 0, 0, 0, 0, 0, 1, 0, 0, 0, 0, 0, 0, 0, 0, 0, 0, 0, 0, 0, 0, 0, 0, 0, 0, 0, 0, 0]]}}21}"
        },
        {
            "time": 157.43700003623962,
            "program": "1{2,3{6{8{15,25,26,28}}}21}"
        },
        {
            "time": 157.5199999809265,
            "program": "1{2,3{5{8{9,25,26,28}17}}21}"
        },
        {
            "time": 157.60399985313416,
            "program": "1{2,3{5{8{12,22,27,28}17}}21}"
        },
        {
            "time": 157.65400004386902,
            "program": "1{2,3{6{8{15,25,26,29}}}21}"
        },
        {
            "time": 157.73599982261658,
            "program": "1{2,3{5{8{15,23,26,29}17}}21}"
        }
    ],
    "try_index": 1,
    "runtime": 158.86500000953674,
    "mined_fragments": [
        {
            "fragments": "RuleNode[8{13,22,26,28}, 5{8{13,22,26,28}18}, 3{5{8{13,22,26,28}18}}, 28,, 22,, 13,, 21,, 2,, 18,, 26,, 1{2,3{5{8{13,22,26,28}18}}21}]",
            "time": 27.703999996185303
        },
        {
            "fragments": "RuleNode[8{13,22,26,28}, 28,, 22,, 8{11,22,26,28}, 11,, 1{2,3{5{8{13,22,26,28}18}}21}, 1{2,3{5{8{11,22,26,28}18}}21}, 5{8{13,22,26,28}18}, 3{5{8{13,22,26,28}18}}, 13,, 21,, 2,, 18,, 26,, 5{8{11,22,26,28}18}, 3{5{8{11,22,26,28}18}}]",
            "time": 31.187000036239624
        },
        {
            "fragments": "RuleNode[28,, 5{8{13,22,27,28}17}, 3{5{8{13,22,27,28}17}}, 8{13,22,27,28}, 17,, 22,, 1{2,3{5{8{13,22,27,28}17}}21}, 13,, 21,, 2,, 27,]",
            "time": 53.39699983596802
        },
        {
            "fragments": "RuleNode[5{8{13,23,27,28}17}, 3{5{8{13,23,27,28}17}}, 28,, 17,, 23,, 1{2,3{5{8{13,23,27,28}17}}21}, 13,, 21,, 2,, 27,, 8{13,23,27,28}]",
            "time": 55.007999897003174
        },
        {
            "fragments": "RuleNode[28,, 17,, 23,, 1{2,4{5{8{13,23,27,28}17}3{5{8{13,23,27,28}17}}}21}, 5{8{13,23,27,28}17}, 3{5{8{13,23,27,28}17}}, 4{5{8{13,23,27,28}17}3{5{8{13,23,27,28}17}}}, 1{2,3{5{8{13,23,27,28}17}}21}, 13,, 21,, 2,, 27,, 8{13,23,27,28}]",
            "time": 69.40999984741211
        },
        {
            "fragments": "RuleNode[28,, 17,, 23,, 1{2,4{5{8{13,23,27,28}17}3{5{8{13,23,27,28}17}}}21}, 5{8{13,23,27,28}17}, 3{5{8{13,23,27,28}17}}, 4{5{8{13,23,27,28}17}3{5{8{13,23,27,28}17}}}, 13,, 21,, 2,, 27,, 5{8{13,23,26,28}17}, 3{5{8{13,23,26,28}17}}, 8{13,23,26,28}, 8{13,23,27,28}, 26,, 1{2,3{5{8{13,23,26,28}17}}21}]",
            "time": 82.5939998626709
        },
        {
            "fragments": "RuleNode[29,, 25,, 4{6{8{14,23,27,28}}3{5{8{13,25,27,29}17}}}, 5{8{13,25,27,29}17}, 3{5{8{13,25,27,29}17}}, 28,, 1{2,4{6{8{14,23,27,28}}3{5{8{13,25,27,29}17}}}21}, 8{14,23,27,28}, 17,, 23,, 13,, 21,, 2,, 6{8{14,23,27,28}}, 27,, 8{13,25,27,29}, 14,]",
            "time": 119.58999991416931
        },
        {
            "fragments": "RuleNode[28,, 17,, 8{15,22,27,28}, 22,, 15,, 21,, 2,, 27,, 5{8{15,22,27,28}17}, 3{5{8{15,22,27,28}17}}, 1{2,3{5{8{15,22,27,28}17}}21}]",
            "time": 136.73399996757507
        },
        {
            "fragments": "RuleNode[5{8{15,25,27,28}17}, 3{5{8{15,25,27,28}17}}, 8{15,25,27,28}, 25,, 28,, 17,, 1{2,3{5{8{15,25,27,28}17}}21}, 15,, 2,, 27,, 21,]",
            "time": 143.01699995994568
        },
        {
            "fragments": "RuleNode[25,, 28,, 17,, 5{8{15,25,26,28}17}, 3{5{8{15,25,26,28}17}}, 2,, 15,, 21,, 26,, 1{2,3{5{8{15,25,26,28}17}}21}, 8{15,25,26,28}]",
            "time": 152.8399999141693
        }
    ],
    "grammar": "1: Program = begin\n    state = Init\n    Blocks\n    End\nend\n2: Init = mc_init(start_pos)\n3: Blocks = Block\n4: Blocks = begin\n    Block\n    Blocks\nend\n5: Block = while true\n    Move\n    Bool || break\nend\n6: Block = Move\n7: Block = if Bool\n    Move\nend\n8: Move = mc_move!(state, Direction, Times, Sprint, Jump)\n9: Direction = [\"forward\"]\n10: Direction = [\"back\"]\n11: Direction = [\"left\"]\n12: Direction = [\"right\"]\n13: Direction = [\"forward\", \"left\"]\n14: Direction = [\"forward\", \"right\"]\n15: Direction = [\"back\", \"left\"]\n16: Direction = [\"back\", \"right\"]\n17: Bool = mc_was_good_move(state)\n18: Bool = mc_has_moved(state)\n19: Bool = mc_is_done(state)\n20: Bool = !Bool\n21: End = mc_end(state)\n22: Times = 1\n23: Times = 2\n24: Times = 3\n25: Times = 4\n26: Sprint = true\n27: Sprint = false\n28: Jump = true\n29: Jump = false\n",
    "evaluated_programs": [
        {
            "time": 0.6989998817443848,
            "reward": -10.114494323730469,
            "program": "1{2,4{5{8{16,25,26,29}18}3{5{8{10,25,26,29}17}}}21}"
        },
        {
            "time": 0.7609999179840088,
            "reward": -0.10802459716796875,
            "program": "1{2,3{6{8{12,22,26,28}}}21}"
        },
        {
            "time": 0.8239998817443848,
            "reward": 0.08835601806640625,
            "program": "1{2,3{6{8{15,23,26,29}}}21}"
        },
        {
            "time": 0.8910000324249268,
            "reward": 0.0350799560546875,
            "program": "1{2,3{6{8{9,23,27,28}}}21}"
        },
        {
            "time": 0.9529998302459717,
            "reward": 0.0117950439453125,
            "program": "1{2,3{6{8{14,23,27,28}}}21}"
        },
        {
            "time": 2.3569998741149902,
            "reward": -10.04248046875,
            "program": "1{2,4{5{8{10,23,26,29}18}3{6{8{12,25,27,29}}}}21}"
        },
        {
            "time": 2.4759998321533203,
            "reward": 0.2305908203125,
            "program": "1{2,3{6{8{9,24,26,29}}}21}"
        },
        {
            "time": 2.5279998779296875,
            "reward": 0.07001495361328125,
            "program": "1{2,3{6{8{11,22,27,28}}}21}"
        },
        {
            "time": 2.5820000171661377,
            "reward": -0.05976104736328125,
            "program": "1{2,3{6{8{10,22,26,28}}}21}"
        },
        {
            "time": 3.567999839782715,
            "reward": 5.050811767578125,
            "program": "1{2,3{5{8{15,22,27,28}18}}21}"
        },
        {
            "time": 4.588000059127808,
            "reward": 0.15185546875,
            "program": "1{2,3{6{8{15,24,26,29}}}21}"
        },
        {
            "time": 4.628999948501587,
            "reward": 0.0,
            "program": "1{2,3{7{18,8{15,25,26,28}}}21}"
        },
        {
            "time": 5.292999982833862,
            "reward": -10.090766906738281,
            "program": "1{2,4{5{8{16,22,27,28}18}3{6{8{12,22,26,29}}}}21}"
        },
        {
            "time": 5.365999937057495,
            "reward": -0.19124603271484375,
            "program": "1{2,3{6{8{12,23,26,28}}}21}"
        },
        {
            "time": 5.418999910354614,
            "reward": -0.08905792236328125,
            "program": "1{2,3{6{8{12,22,26,29}}}21}"
        },
        {
            "time": 7.415999889373779,
            "reward": -0.1412353515625,
            "program": "1{2,3{6{8{14,24,27,28}}}21}"
        },
        {
            "time": 7.48799991607666,
            "reward": 0.16204833984375,
            "program": "1{2,4{6{8{13,22,27,28}}3{7{18,8{15,23,27,28}}}}21}"
        },
        {
            "time": 7.865999937057495,
            "reward": 5.581939697265625,
            "program": "1{2,3{5{8{11,22,27,29}18}}21}"
        },
        {
            "time": 7.937999963760376,
            "reward": 0.158538818359375,
            "program": "1{2,4{6{8{15,23,26,29}}3{6{8{9,22,27,29}}}}21}"
        },
        {
            "time": 8.652999877929688,
            "reward": 4.598396301269531,
            "program": "1{2,3{5{8{9,22,27,29}17}}21}"
        },
        {
            "time": 8.69599986076355,
            "reward": 0.0,
            "program": "1{2,4{7{17,8{15,23,26,28}}3{7{19,8{9,23,26,29}}}}21}"
        },
        {
            "time": 8.928999900817871,
            "reward": -2.0693130493164062,
            "program": "1{2,3{5{8{14,22,26,29}18}}21}"
        },
        {
            "time": 8.968999862670898,
            "reward": 0.0,
            "program": "1{2,3{7{19,8{16,23,26,28}}}21}"
        },
        {
            "time": 8.990000009536743,
            "reward": 0.0,
            "program": "1{2,4{7{19,8{16,25,27,29}}3{7{17,8{14,22,26,28}}}}21}"
        },
        {
            "time": 9.031999826431274,
            "reward": -0.16350555419921875,
            "program": "1{2,3{6{8{16,23,26,29}}}21}"
        },
        {
            "time": 9.073999881744385,
            "reward": 0.0,
            "program": "1{2,3{7{19,8{12,22,27,28}}}21}"
        },
        {
            "time": 9.105000019073486,
            "reward": 0.07460784912109375,
            "program": "1{2,4{7{17,8{12,22,27,29}}3{6{8{13,22,27,28}}}}21}"
        },
        {
            "time": 11.702999830245972,
            "reward": 0.07001495361328125,
            "program": "1{2,3{6{8{11,22,26,28}}}21}"
        },
        {
            "time": 11.78600001335144,
            "reward": -0.29418182373046875,
            "program": "1{2,3{6{8{14,25,26,29}}}21}"
        },
        {
            "time": 11.829999923706055,
            "reward": 0.0,
            "program": "1{2,3{7{19,8{15,23,27,29}}}21}"
        },
        {
            "time": 11.894999980926514,
            "reward": 0.47527313232421875,
            "program": "1{2,3{6{8{11,25,27,29}}}21}"
        },
        {
            "time": 11.95799994468689,
            "reward": 0.22662353515625,
            "program": "1{2,3{6{8{11,23,27,29}}}21}"
        },
        {
            "time": 12.008999824523926,
            "reward": -0.04077911376953125,
            "program": "1{2,3{6{8{10,22,26,29}}}21}"
        },
        {
            "time": 12.098999977111816,
            "reward": -0.20925140380859375,
            "program": "1{2,4{5{8{15,22,27,29}19}4{6{8{14,24,27,29}}3{7{20{17}8{16,22,26,29}}}}}21}"
        },
        {
            "time": 12.192999839782715,
            "reward": -0.4962921142578125,
            "program": "1{2,4{6{8{16,25,27,28}}3{6{8{10,22,27,28}}}}21}"
        },
        {
            "time": 16.35699987411499,
            "reward": 0.7820968627929688,
            "program": "1{2,4{6{8{13,25,27,29}}3{6{8{15,23,27,28}}}}21}"
        },
        {
            "time": 16.430999994277954,
            "reward": 0.19617462158203125,
            "program": "1{2,3{6{8{13,24,27,28}}}21}"
        },
        {
            "time": 16.516000032424927,
            "reward": 0.2204742431640625,
            "program": "1{2,3{5{8{15,25,27,29}19}}21}"
        },
        {
            "time": 16.590999841690063,
            "reward": 0.5340805053710938,
            "program": "1{2,3{6{8{13,24,26,29}}}21}"
        },
        {
            "time": 21.26799988746643,
            "reward": 0.0,
            "program": "1{2,3{7{19,8{12,24,27,28}}}21}"
        },
        {
            "time": 21.329999923706055,
            "reward": 0.2800750732421875,
            "program": "1{2,3{7{20{19}8{9,25,26,29}}}21}"
        },
        {
            "time": 21.38699984550476,
            "reward": 0.18541717529296875,
            "program": "1{2,3{6{8{13,22,26,28}}}21}"
        },
        {
            "time": 21.780999898910522,
            "reward": 5.581939697265625,
            "program": "1{2,3{5{8{11,24,26,29}17}}21}"
        },
        {
            "time": 21.83399987220764,
            "reward": -0.10802459716796875,
            "program": "1{2,3{6{8{12,22,27,28}}}21}"
        },
        {
            "time": 21.878000020980835,
            "reward": 0.0,
            "program": "1{2,3{7{17,8{12,23,26,28}}}21}"
        },
        {
            "time": 21.91100001335144,
            "reward": -0.04077911376953125,
            "program": "1{2,3{6{8{10,22,27,29}}}21}"
        },
        {
            "time": 21.99899983406067,
            "reward": 0.28014373779296875,
            "program": "1{2,3{6{8{13,25,27,28}}}21}"
        },
        {
            "time": 22.694999933242798,
            "reward": -10.090766906738281,
            "program": "1{2,3{5{8{16,22,27,28}18}}21}"
        },
        {
            "time": 22.77900004386902,
            "reward": -0.2830047607421875,
            "program": "1{2,3{6{8{12,24,26,28}}}21}"
        },
        {
            "time": 22.83299994468689,
            "reward": -0.05976104736328125,
            "program": "1{2,3{6{8{10,22,27,28}}}21}"
        },
        {
            "time": 25.747999906539917,
            "reward": -0.31369781494140625,
            "program": "1{2,3{5{8{15,24,27,29}18}}21}"
        },
        {
            "time": 25.88100004196167,
            "reward": 0.17960357666015625,
            "program": "1{2,4{5{8{13,22,27,29}19}3{6{8{15,22,26,29}}}}21}"
        },
        {
            "time": 25.97499990463257,
            "reward": -0.0592498779296875,
            "program": "1{2,4{6{8{14,25,26,28}}3{6{8{12,22,26,28}}}}21}"
        },
        {
            "time": 26.68400001525879,
            "reward": -0.11606597900390625,
            "program": "1{2,3{5{8{14,23,26,29}17}}21}"
        },
        {
            "time": 27.70299983024597,
            "reward": 17.950942993164062,
            "program": "1{2,3{5{8{13,22,26,28}18}}21}"
        },
        {
            "time": 28.139999866485596,
            "reward": 5.581939697265625,
            "program": "1{2,3{5{8{11,25,26,29}18}}21}"
        },
        {
            "time": 30.182999849319458,
            "reward": 0.0,
            "program": "1{2,3{7{17,8{9,23,26,29}}}21}"
        },
        {
            "time": 30.203999996185303,
            "reward": 0.0,
            "program": "1{2,3{7{17,8{9,22,27,28}}}21}"
        },
        {
            "time": 31.187000036239624,
            "reward": 13.580368041992188,
            "program": "1{2,3{5{8{11,22,26,28}18}}21}"
        },
        {
            "time": 33.19799995422363,
            "reward": -0.1040496826171875,
            "program": "1{2,4{6{8{10,23,26,29}}3{7{17,8{10,25,26,29}}}}21}"
        },
        {
            "time": 34.26099991798401,
            "reward": 20.291881561279297,
            "program": "1{2,3{5{8{13,22,26,29}18}}21}"
        },
        {
            "time": 34.40599989891052,
            "reward": 0.8629531860351562,
            "program": "1{2,4{6{8{13,25,26,28}}3{6{8{12,24,27,28}}}}21}"
        },
        {
            "time": 35.12999987602234,
            "reward": 0.0,
            "program": "1{2,4{7{17,8{16,22,27,29}}3{7{18,8{16,24,27,28}}}}21}"
        },
        {
            "time": 42.460999965667725,
            "reward": -2.0693130493164062,
            "program": "1{2,3{5{8{14,25,27,28}18}}21}"
        },
        {
            "time": 43.57799983024597,
            "reward": 17.879253387451172,
            "program": "1{2,3{6{8{12,24,26,29}}}21}"
        },
        {
            "time": 47.22199988365173,
            "reward": 17.959999084472656,
            "program": "1{2,3{6{8{9,22,27,29}}}21}"
        },
        {
            "time": 47.263999938964844,
            "reward": 17.950942993164062,
            "program": "1{2,3{7{17,8{15,24,26,28}}}21}"
        },
        {
            "time": 47.34599995613098,
            "reward": 18.067790985107422,
            "program": "1{2,4{5{8{11,23,26,28}19}3{5{8{12,23,26,28}19}}}21}"
        },
        {
            "time": 47.42999982833862,
            "reward": 17.87732696533203,
            "program": "1{2,3{6{8{14,25,27,28}}}21}"
        },
        {
            "time": 47.49399995803833,
            "reward": 17.972610473632812,
            "program": "1{2,3{6{8{9,23,26,29}}}21}"
        },
        {
            "time": 47.53600001335144,
            "reward": 17.950942993164062,
            "program": "1{2,3{7{17,8{10,24,27,29}}}21}"
        },
        {
            "time": 47.615999937057495,
            "reward": 17.852108001708984,
            "program": "1{2,3{5{8{16,25,27,29}19}}21}"
        },
        {
            "time": 47.66799998283386,
            "reward": 17.97919464111328,
            "program": "1{2,3{6{8{11,22,27,28}}}21}"
        },
        {
            "time": 47.73799991607666,
            "reward": 17.879253387451172,
            "program": "1{2,3{6{8{12,24,27,29}}}21}"
        },
        {
            "time": 47.83099985122681,
            "reward": 17.956684112548828,
            "program": "1{2,3{5{8{10,22,26,28}17}}21}"
        },
        {
            "time": 52.430999994277954,
            "reward": 18.09619140625,
            "program": "1{2,3{6{8{11,24,26,28}}}21}"
        },
        {
            "time": 53.39699983596802,
            "reward": 28.31747055053711,
            "program": "1{2,3{5{8{13,22,27,28}17}}21}"
        },
        {
            "time": 53.50499987602234,
            "reward": 17.97385025024414,
            "program": "1{2,3{6{8{13,22,27,28}}}21}"
        },
        {
            "time": 53.58800005912781,
            "reward": 17.901519775390625,
            "program": "1{2,3{5{8{14,24,26,29}20{18}}}21}"
        },
        {
            "time": 55.00699996948242,
            "reward": 33.11579132080078,
            "program": "1{2,3{5{8{13,23,27,28}17}}21}"
        },
        {
            "time": 55.11999988555908,
            "reward": 18.00402069091797,
            "program": "1{2,3{5{8{9,25,26,28}19}}21}"
        },
        {
            "time": 55.223999977111816,
            "reward": 17.90456771850586,
            "program": "1{2,3{5{8{10,23,26,28}17}}21}"
        },
        {
            "time": 60.776000022888184,
            "reward": 18.008052825927734,
            "program": "1{2,3{5{8{9,22,26,29}17}}21}"
        },
        {
            "time": 66.88599991798401,
            "reward": 17.950942993164062,
            "program": "1{2,3{7{17,8{13,22,26,28}}}21}"
        },
        {
            "time": 67.65899991989136,
            "reward": 7.811260223388672,
            "program": "1{2,3{5{8{16,24,26,29}20{19}}}21}"
        },
        {
            "time": 69.40999984741211,
            "reward": 36.23815155029297,
            "program": "1{2,4{5{8{13,23,27,28}17}3{5{8{13,23,27,28}17}}}21}"
        },
        {
            "time": 72.23300004005432,
            "reward": 17.95014190673828,
            "program": "1{2,4{6{8{16,22,26,28}}3{6{8{9,25,26,28}}}}21}"
        },
        {
            "time": 78.40400004386902,
            "reward": 17.948863983154297,
            "program": "1{2,4{5{8{16,23,27,28}17}3{5{8{13,23,27,28}19}}}21}"
        },
        {
            "time": 82.5939998626709,
            "reward": 29.51598358154297,
            "program": "1{2,3{5{8{13,23,26,28}17}}21}"
        },
        {
            "time": 82.68299984931946,
            "reward": 18.05213165283203,
            "program": "1{2,4{5{8{13,23,27,28}20{17}}3{6{8{9,22,27,28}}}}21}"
        },
        {
            "time": 84.28799986839294,
            "reward": 34.087806701660156,
            "program": "1{2,4{5{8{13,23,27,28}17}3{5{8{13,22,27,29}18}}}21}"
        },
        {
            "time": 88.12399983406067,
            "reward": 35.8995361328125,
            "program": "1{2,4{5{8{15,23,26,29}20{19}}4{6{8{10,22,27,29}}3{6{8{11,24,27,29}}}}}21}"
        },
        {
            "time": 88.2059998512268,
            "reward": 36.32448196411133,
            "program": "1{2,3{6{8{13,25,27,29}}}21}"
        },
        {
            "time": 88.28600001335144,
            "reward": 36.0618896484375,
            "program": "1{2,4{5{8{12,23,26,28}19}3{6{8{14,23,26,28}}}}21}"
        },
        {
            "time": 88.36800003051758,
            "reward": 36.33249282836914,
            "program": "1{2,3{6{8{9,25,27,29}}}21}"
        },
        {
            "time": 88.41799998283386,
            "reward": 36.25589370727539,
            "program": "1{2,4{7{19,8{12,24,27,29}}3{6{8{13,22,26,28}}}}21}"
        },
        {
            "time": 88.53199982643127,
            "reward": 36.25606918334961,
            "program": "1{2,4{6{8{9,24,26,28}}3{6{8{10,25,26,29}}}}21}"
        },
        {
            "time": 88.57399988174438,
            "reward": 36.23815155029297,
            "program": "1{2,3{7{19,8{16,22,27,29}}}21}"
        },
        {
            "time": 88.61399984359741,
            "reward": 36.23815155029297,
            "program": "1{2,3{7{17,8{12,25,26,28}}}21}"
        },
        {
            "time": 88.67400002479553,
            "reward": 36.27006530761719,
            "program": "1{2,3{6{8{10,23,26,29}}}21}"
        },
        {
            "time": 88.72599983215332,
            "reward": 36.234867095947266,
            "program": "1{2,4{7{17,8{11,24,26,29}}3{5{8{12,22,27,29}19}}}21}"
        },
        {
            "time": 91.50999999046326,
            "reward": 36.256534576416016,
            "program": "1{2,3{6{8{9,22,26,28}}}21}"
        },
        {
            "time": 91.58500003814697,
            "reward": 36.19352722167969,
            "program": "1{2,3{6{8{12,24,27,29}}}21}"
        },
        {
            "time": 91.64999985694885,
            "reward": 36.231285095214844,
            "program": "1{2,3{6{8{16,23,27,28}}}21}"
        },
        {
            "time": 91.74799990653992,
            "reward": 36.28559494018555,
            "program": "1{2,3{5{8{13,25,27,28}17}}21}"
        },
        {
            "time": 91.80200004577637,
            "reward": 36.251914978027344,
            "program": "1{2,3{6{8{10,22,26,29}}}21}"
        },
        {
            "time": 91.86299991607666,
            "reward": 36.284202575683594,
            "program": "1{2,3{6{8{9,23,26,29}}}21}"
        },
        {
            "time": 91.91499996185303,
            "reward": 36.256534576416016,
            "program": "1{2,3{6{8{9,22,26,29}}}21}"
        },
        {
            "time": 91.95700001716614,
            "reward": 36.23815155029297,
            "program": "1{2,3{7{19,8{9,23,27,28}}}21}"
        },
        {
            "time": 91.99799990653992,
            "reward": 36.23815155029297,
            "program": "1{2,3{7{18,8{9,25,27,29}}}21}"
        },
        {
            "time": 92.07099986076355,
            "reward": 36.21452713012695,
            "program": "1{2,3{6{8{16,24,26,29}}}21}"
        },
        {
            "time": 95.53399991989136,
            "reward": 36.27006530761719,
            "program": "1{2,3{7{20{19}8{10,23,27,28}}}21}"
        },
        {
            "time": 95.72399997711182,
            "reward": 34.9869270324707,
            "program": "1{2,3{5{8{12,23,26,29}18}}21}"
        },
        {
            "time": 95.80999994277954,
            "reward": 36.26417922973633,
            "program": "1{2,3{5{8{11,23,26,28}17}}21}"
        },
        {
            "time": 95.87299990653992,
            "reward": 36.291316986083984,
            "program": "1{2,3{6{8{10,25,27,28}}}21}"
        },
        {
            "time": 95.95299983024597,
            "reward": 36.04825210571289,
            "program": "1{2,3{6{8{12,25,26,29}}}21}"
        },
        {
            "time": 96.0329999923706,
            "reward": 36.33872604370117,
            "program": "1{2,3{6{8{9,25,26,29}}}21}"
        },
        {
            "time": 101.93700003623962,
            "reward": 36.25589370727539,
            "program": "1{2,3{6{8{13,22,26,28}}}21}"
        },
        {
            "time": 104.22000002861023,
            "reward": 36.171424865722656,
            "program": "1{2,4{7{17,8{15,22,27,29}}3{5{8{13,25,26,29}18}}}21}"
        },
        {
            "time": 104.36299991607666,
            "reward": 36.251914978027344,
            "program": "1{2,4{7{17,8{11,23,26,29}}3{7{20{17}8{10,22,26,29}}}}21}"
        },
        {
            "time": 106.07999992370605,
            "reward": 36.238590240478516,
            "program": "1{2,3{6{8{16,22,27,29}}}21}"
        },
        {
            "time": 110.40199995040894,
            "reward": 35.8995361328125,
            "program": "1{2,4{5{8{13,24,27,29}19}3{5{8{10,22,27,29}18}}}21}"
        },
        {
            "time": 111.25499987602234,
            "reward": 35.8016471862793,
            "program": "1{2,4{6{8{9,24,26,28}}3{5{8{12,25,27,29}19}}}21}"
        },
        {
            "time": 111.30799984931946,
            "reward": 36.252559661865234,
            "program": "1{2,4{7{17,8{13,23,27,29}}3{6{8{15,22,27,28}}}}21}"
        },
        {
            "time": 111.3899998664856,
            "reward": 36.26417922973633,
            "program": "1{2,3{6{8{11,25,26,28}}}21}"
        },
        {
            "time": 113.3420000076294,
            "reward": 30.247249603271484,
            "program": "1{2,3{5{8{10,23,27,28}18}}21}"
        },
        {
            "time": 113.4689998626709,
            "reward": 36.10185241699219,
            "program": "1{2,3{6{8{14,25,27,28}}}21}"
        },
        {
            "time": 113.57099986076355,
            "reward": 36.304779052734375,
            "program": "1{2,3{5{8{9,23,26,28}17}}21}"
        },
        {
            "time": 113.64499998092651,
            "reward": 36.31593322753906,
            "program": "1{2,3{7{20{17}8{9,24,27,29}}}21}"
        },
        {
            "time": 113.7189998626709,
            "reward": 36.2225456237793,
            "program": "1{2,3{5{8{14,24,26,29}19}}21}"
        },
        {
            "time": 113.77300000190735,
            "reward": 36.238590240478516,
            "program": "1{2,3{6{8{16,22,26,29}}}21}"
        },
        {
            "time": 113.85800004005432,
            "reward": 36.05827331542969,
            "program": "1{2,3{6{8{16,25,27,28}}}21}"
        },
        {
            "time": 113.9210000038147,
            "reward": 36.231285095214844,
            "program": "1{2,3{6{8{16,23,27,29}}}21}"
        },
        {
            "time": 113.96300005912781,
            "reward": 36.23815155029297,
            "program": "1{2,3{7{17,8{14,23,27,29}}}21}"
        },
        {
            "time": 116.91999983787537,
            "reward": 38.06814193725586,
            "program": "1{2,4{5{8{15,24,26,28}20{20{17}}}3{5{8{11,24,27,29}20{19}}}}21}"
        },
        {
            "time": 116.96300005912781,
            "reward": 36.23815155029297,
            "program": "1{2,3{7{17,8{16,24,26,28}}}21}"
        },
        {
            "time": 117.00399994850159,
            "reward": 36.23815155029297,
            "program": "1{2,3{7{17,8{16,24,27,29}}}21}"
        },
        {
            "time": 117.08699989318848,
            "reward": 36.232879638671875,
            "program": "1{2,3{6{8{10,25,26,28}}}21}"
        },
        {
            "time": 117.18899989128113,
            "reward": 36.34465408325195,
            "program": "1{2,4{5{8{9,24,26,29}19}3{6{8{13,24,26,28}}}}21}"
        },
        {
            "time": 118.00099992752075,
            "reward": 36.201900482177734,
            "program": "1{2,3{6{8{16,24,27,29}}}21}"
        },
        {
            "time": 118.07399988174438,
            "reward": 36.3123779296875,
            "program": "1{2,3{6{8{13,24,27,28}}}21}"
        },
        {
            "time": 119.58899998664856,
            "reward": 48.71662139892578,
            "program": "1{2,4{6{8{14,23,27,28}}3{5{8{13,25,27,29}17}}}21}"
        },
        {
            "time": 120.71599984169006,
            "reward": 47.009033203125,
            "program": "1{2,4{6{8{14,23,27,28}}3{5{8{13,22,27,29}17}}}21}"
        },
        {
            "time": 120.85800004005432,
            "reward": 36.30303955078125,
            "program": "1{2,4{6{8{11,22,27,29}}3{5{8{11,25,27,29}18}}}21}"
        },
        {
            "time": 120.9229998588562,
            "reward": 36.24098205566406,
            "program": "1{2,3{5{8{14,23,27,28}19}}21}"
        },
        {
            "time": 121.01999998092651,
            "reward": 36.083065032958984,
            "program": "1{2,4{6{8{13,22,27,29}}3{6{8{12,24,27,28}}}}21}"
        },
        {
            "time": 121.08599996566772,
            "reward": 36.25547790527344,
            "program": "1{2,4{6{8{12,22,27,28}}3{5{8{13,22,27,28}19}}}21}"
        },
        {
            "time": 121.36500000953674,
            "reward": 35.057064056396484,
            "program": "1{2,4{6{8{14,25,27,28}}3{5{8{12,23,26,29}18}}}21}"
        },
        {
            "time": 121.43899989128113,
            "reward": 36.21452713012695,
            "program": "1{2,3{5{8{16,24,27,28}17}}21}"
        },
        {
            "time": 121.52600002288818,
            "reward": 36.32448196411133,
            "program": "1{2,3{7{20{17}8{13,25,27,29}}}21}"
        },
        {
            "time": 121.58899998664856,
            "reward": 36.24098205566406,
            "program": "1{2,3{6{8{14,23,27,28}}}21}"
        },
        {
            "time": 125.6579999923706,
            "reward": 48.524919509887695,
            "program": "1{2,4{6{8{9,24,27,28}}3{5{8{13,25,26,29}20{20{17}}}}}21}"
        },
        {
            "time": 125.81200003623962,
            "reward": 36.271705627441406,
            "program": "1{2,3{5{8{10,25,27,29}17}}21}"
        },
        {
            "time": 128.28099989891052,
            "reward": 48.71662139892578,
            "program": "1{2,3{7{19,8{12,25,26,28}}}21}"
        },
        {
            "time": 128.3309998512268,
            "reward": 48.575164794921875,
            "program": "1{2,4{6{8{9,22,27,29}}3{6{8{16,23,26,29}}}}21}"
        },
        {
            "time": 128.37999987602234,
            "reward": 48.71478271484375,
            "program": "1{2,3{6{8{13,22,27,29}}}21}"
        },
        {
            "time": 128.44299983978271,
            "reward": 48.79231834411621,
            "program": "1{2,3{6{8{10,23,26,28}}}21}"
        },
        {
            "time": 128.48499989509583,
            "reward": 48.71662139892578,
            "program": "1{2,3{7{19,8{10,23,26,28}}}21}"
        },
        {
            "time": 130.47099995613098,
            "reward": 43.13964653015137,
            "program": "1{2,3{5{8{11,23,27,29}18}}21}"
        },
        {
            "time": 130.58599996566772,
            "reward": 48.111690521240234,
            "program": "1{2,3{6{8{9,24,26,28}}}21}"
        },
        {
            "time": 130.6380000114441,
            "reward": 48.594017028808594,
            "program": "1{2,3{5{8{14,22,27,28}17}}21}"
        },
        {
            "time": 130.67899990081787,
            "reward": 48.71662139892578,
            "program": "1{2,3{7{18,8{13,25,27,29}}}21}"
        },
        {
            "time": 130.7389998435974,
            "reward": 48.25469207763672,
            "program": "1{2,3{6{8{13,25,26,28}}}21}"
        },
        {
            "time": 130.84099984169006,
            "reward": 49.103363037109375,
            "program": "1{2,4{6{8{10,25,27,29}}3{6{8{9,23,27,29}}}}21}"
        },
        {
            "time": 130.91299986839294,
            "reward": 48.83255195617676,
            "program": "1{2,3{6{8{10,24,27,28}}}21}"
        },
        {
            "time": 130.98399996757507,
            "reward": 48.14653968811035,
            "program": "1{2,3{6{8{14,24,26,29}}}21}"
        },
        {
            "time": 132.97000002861023,
            "reward": 48.71927452087402,
            "program": "1{2,3{6{8{16,23,26,29}}}21}"
        },
        {
            "time": 133.03199982643127,
            "reward": 48.28628730773926,
            "program": "1{2,3{6{8{9,23,26,28}}}21}"
        },
        {
            "time": 136.73399996757507,
            "reward": 65.14418172836304,
            "program": "1{2,3{5{8{15,22,27,28}17}}21}"
        },
        {
            "time": 138.72499990463257,
            "reward": 48.46443557739258,
            "program": "1{2,3{6{8{9,24,27,28}}}21}"
        },
        {
            "time": 138.77600002288818,
            "reward": 48.594017028808594,
            "program": "1{2,3{6{8{14,22,27,28}}}21}"
        },
        {
            "time": 138.88899993896484,
            "reward": 47.871002197265625,
            "program": "1{2,4{7{20{18}8{12,25,27,29}}3{7{18,8{12,24,26,28}}}}21}"
        },
        {
            "time": 138.93899989128113,
            "reward": 48.6951904296875,
            "program": "1{2,3{5{8{16,22,26,28}17}}21}"
        },
        {
            "time": 139.00999999046326,
            "reward": 48.415536880493164,
            "program": "1{2,3{6{8{12,24,27,29}}}21}"
        },
        {
            "time": 141.72199988365173,
            "reward": 48.65189743041992,
            "program": "1{2,3{6{8{16,24,27,28}}}21}"
        },
        {
            "time": 143.01699995994568,
            "reward": 68.58508825302124,
            "program": "1{2,3{5{8{15,25,27,28}17}}21}"
        },
        {
            "time": 143.125,
            "reward": 48.14653968811035,
            "program": "1{2,3{5{8{14,24,26,29}17}}21}"
        },
        {
            "time": 143.20899987220764,
            "reward": 47.80548667907715,
            "program": "1{2,3{6{8{14,25,26,28}}}21}"
        },
        {
            "time": 145.97599983215332,
            "reward": 48.47024154663086,
            "program": "1{2,4{6{8{12,23,26,28}}3{6{8{12,22,27,29}}}}21}"
        },
        {
            "time": 146.08699989318848,
            "reward": 48.985355377197266,
            "program": "1{2,4{6{8{10,25,26,29}}3{6{8{14,24,27,28}}}}21}"
        },
        {
            "time": 146.14800000190735,
            "reward": 48.28628730773926,
            "program": "1{2,3{5{8{9,23,26,28}17}}21}"
        },
        {
            "time": 147.39699983596802,
            "reward": 68.64958190917969,
            "program": "1{2,3{5{8{15,24,27,28}17}}21}"
        },
        {
            "time": 147.49699997901917,
            "reward": 48.44063949584961,
            "program": "1{2,4{6{8{13,23,26,28}}3{7{20{18}8{14,25,27,28}}}}21}"
        },
        {
            "time": 147.53799986839294,
            "reward": 48.71662139892578,
            "program": "1{2,3{7{17,8{15,25,27,28}}}21}"
        },
        {
            "time": 152.8399999141693,
            "reward": 68.58508825302124,
            "program": "1{2,3{5{8{15,25,26,28}17}}21}"
        },
        {
            "time": 154.0920000076294,
            "reward": 68.75769901275635,
            "program": "1{2,3{5{8{15,23,26,28}17}}21}"
        },
        {
            "time": 155.47199988365173,
            "reward": 68.84060454368591,
            "program": "1{2,4{5{8{15,25,26,28}17}3{6{8{13,25,26,29}}}}21}"
        },
        {
            "time": 157.5199999809265,
            "reward": 48.994524002075195,
            "program": "1{2,3{6{8{15,25,26,28}}}21}"
        },
        {
            "time": 157.60399985313416,
            "reward": 47.93704605102539,
            "program": "1{2,3{5{8{9,25,26,28}17}}21}"
        },
        {
            "time": 157.65400004386902,
            "reward": 48.625661849975586,
            "program": "1{2,3{5{8{12,22,27,28}17}}21}"
        },
        {
            "time": 157.73599982261658,
            "reward": 49.35556983947754,
            "program": "1{2,3{6{8{15,25,26,29}}}21}"
        },
        {
            "time": 158.8639998435974,
            "reward": 169.70770812034607,
            "program": "1{2,3{5{8{15,23,26,29}17}}21}"
        }
    ]
}
