{
    "checkpoint_times": [
        0.0009999275207519531,
        42.68499994277954,
        65.31299996376038
    ],
    "world_seed": 958129,
    "frangel_config": {
        "max_time": 40.0,
        "try_to_simplify": false,
        "compare_programs_by_length": true,
        "verbose_level": 0,
        "generation": {
            "max_size": 40,
            "use_fragments_chance": 0.3,
            "use_entire_fragment_chance": 0.5,
            "use_angelic_conditions_chance": 0.2,
            "similar_new_extra_size": 8,
            "gen_similar_prob_new": 0.5
        },
        "angelic": {
            "max_time": 0.1,
            "boolean_expr_max_size": 6,
            "max_execute_attempts": 4,
            "max_allowed_fails": 0.75,
            "angelic_rulenode": null
        }
    },
    "frangel_seed": 2541,
    "solved": true,
    "used_fragments": [
        {
            "fragment": "8{11,24,26,29}",
            "time": 2.319999933242798
        },
        {
            "fragment": "21,",
            "time": 2.319999933242798
        },
        {
            "fragment": "2,",
            "time": 2.4240000247955322
        },
        {
            "fragment": "5{8{11,24,26,29}17}",
            "time": 2.4240000247955322
        },
        {
            "fragment": "2,",
            "time": 3.1570000648498535
        },
        {
            "fragment": "8{11,24,26,29}",
            "time": 3.1570000648498535
        },
        {
            "fragment": "3{5{8{11,24,26,29}17}}",
            "time": 3.1570000648498535
        },
        {
            "fragment": "8{11,24,26,29}",
            "time": 3.2769999504089355
        },
        {
            "fragment": "29,",
            "time": 3.2769999504089355
        },
        {
            "fragment": "3{5{8{11,24,26,29}17}}",
            "time": 3.3389999866485596
        },
        {
            "fragment": "8{11,24,26,29}",
            "time": 6.691999912261963
        },
        {
            "fragment": "21,",
            "time": 6.691999912261963
        },
        {
            "fragment": "8{11,24,26,29}",
            "time": 6.759000062942505
        },
        {
            "fragment": "1{2,3{5{8{11,24,26,29}17}}21}",
            "time": 6.835999965667725
        },
        {
            "fragment": "11,",
            "time": 6.915999889373779
        },
        {
            "fragment": "2,",
            "time": 7.901000022888184
        },
        {
            "fragment": "5{8{11,24,26,29}17}",
            "time": 7.901000022888184
        },
        {
            "fragment": "5{8{11,24,26,29}17}",
            "time": 7.901000022888184
        },
        {
            "fragment": "1{2,3{5{8{11,24,26,29}17}}21}",
            "time": 9.865999937057495
        },
        {
            "fragment": "2,",
            "time": 9.865999937057495
        },
        {
            "fragment": "3{5{8{11,24,26,29}17}}",
            "time": 9.865999937057495
        },
        {
            "fragment": "1{2,3{5{8{11,24,26,29}17}}21}",
            "time": 9.865999937057495
        },
        {
            "fragment": "24,",
            "time": 9.971999883651733
        },
        {
            "fragment": "1{2,3{5{8{11,24,26,29}17}}21}",
            "time": 10.039999961853027
        },
        {
            "fragment": "1{2,3{5{8{11,24,26,29}17}}21}",
            "time": 10.990000009536743
        },
        {
            "fragment": "11,",
            "time": 11.04800009727478
        },
        {
            "fragment": "21,",
            "time": 11.04800009727478
        },
        {
            "fragment": "8{11,24,26,29}",
            "time": 11.118000030517578
        },
        {
            "fragment": "1{2,3{5{8{11,24,26,29}17}}21}",
            "time": 11.158999919891357
        },
        {
            "fragment": "17,",
            "time": 11.158999919891357
        },
        {
            "fragment": "26,",
            "time": 11.158999919891357
        },
        {
            "fragment": "1{2,3{5{8{11,24,26,29}17}}21}",
            "time": 16.000999927520752
        },
        {
            "fragment": "1{2,3{5{8{11,24,26,29}17}}21}",
            "time": 16.944999933242798
        },
        {
            "fragment": "1{2,3{5{8{11,24,26,29}17}}21}",
            "time": 17.03500008583069
        },
        {
            "fragment": "26,",
            "time": 17.03500008583069
        },
        {
            "fragment": "2,",
            "time": 17.094000101089478
        },
        {
            "fragment": "3{5{8{11,24,26,29}17}}",
            "time": 17.094000101089478
        },
        {
            "fragment": "26,",
            "time": 17.094000101089478
        },
        {
            "fragment": "21,",
            "time": 17.094000101089478
        },
        {
            "fragment": "2,",
            "time": 17.141000032424927
        },
        {
            "fragment": "3{5{8{11,24,26,29}17}}",
            "time": 17.141000032424927
        },
        {
            "fragment": "5{8{11,24,26,29}17}",
            "time": 17.191999912261963
        },
        {
            "fragment": "24,",
            "time": 19.749000072479248
        },
        {
            "fragment": "29,",
            "time": 19.749000072479248
        },
        {
            "fragment": "21,",
            "time": 19.749000072479248
        },
        {
            "fragment": "2,",
            "time": 19.818000078201294
        },
        {
            "fragment": "3{5{8{11,24,26,29}17}}",
            "time": 19.818000078201294
        },
        {
            "fragment": "21,",
            "time": 19.818000078201294
        },
        {
            "fragment": "5{8{11,24,26,29}17}",
            "time": 19.818000078201294
        },
        {
            "fragment": "21,",
            "time": 19.818000078201294
        },
        {
            "fragment": "3{5{8{11,24,26,29}17}}",
            "time": 21.947999954223633
        },
        {
            "fragment": "1{2,3{5{8{11,24,26,29}17}}21}",
            "time": 21.947999954223633
        },
        {
            "fragment": "3{5{8{11,24,26,29}17}}",
            "time": 21.947999954223633
        },
        {
            "fragment": "1{2,3{5{8{11,24,26,29}17}}21}",
            "time": 21.947999954223633
        },
        {
            "fragment": "1{2,3{5{8{11,24,26,29}17}}21}",
            "time": 21.947999954223633
        },
        {
            "fragment": "3{5{8{11,24,26,29}17}}",
            "time": 22.009999990463257
        },
        {
            "fragment": "3{5{8{11,24,26,29}17}}",
            "time": 22.009999990463257
        },
        {
            "fragment": "21,",
            "time": 22.009999990463257
        },
        {
            "fragment": "17,",
            "time": 22.09599995613098
        },
        {
            "fragment": "11,",
            "time": 22.09599995613098
        },
        {
            "fragment": "24,",
            "time": 22.09599995613098
        },
        {
            "fragment": "26,",
            "time": 22.09599995613098
        },
        {
            "fragment": "29,",
            "time": 22.09599995613098
        },
        {
            "fragment": "21,",
            "time": 22.09599995613098
        },
        {
            "fragment": "17,",
            "time": 22.09599995613098
        },
        {
            "fragment": "24,",
            "time": 22.09599995613098
        },
        {
            "fragment": "21,",
            "time": 22.09599995613098
        },
        {
            "fragment": "3{5{8{11,24,26,29}17}}",
            "time": 22.138999938964844
        },
        {
            "fragment": "3{5{8{11,24,26,29}17}}",
            "time": 22.180999994277954
        },
        {
            "fragment": "3{5{8{11,24,26,29}17}}",
            "time": 22.252000093460083
        },
        {
            "fragment": "21,",
            "time": 22.252000093460083
        },
        {
            "fragment": "3{5{8{13,25,27,29}17}}",
            "time": 24.48099994659424
        },
        {
            "fragment": "8{13,25,27,29}",
            "time": 25.07200002670288
        },
        {
            "fragment": "2,",
            "time": 25.177000045776367
        },
        {
            "fragment": "3{5{8{13,25,27,29}17}}",
            "time": 25.177000045776367
        },
        {
            "fragment": "21,",
            "time": 25.177000045776367
        },
        {
            "fragment": "3{5{8{13,25,27,29}17}}",
            "time": 25.177000045776367
        },
        {
            "fragment": "21,",
            "time": 25.177000045776367
        },
        {
            "fragment": "3{5{8{13,25,27,29}17}}",
            "time": 25.253999948501587
        },
        {
            "fragment": "3{5{8{13,25,27,29}17}}",
            "time": 25.296000003814697
        },
        {
            "fragment": "8{13,25,27,29}",
            "time": 25.296000003814697
        },
        {
            "fragment": "3{5{8{13,25,27,29}17}}",
            "time": 25.296000003814697
        },
        {
            "fragment": "2,",
            "time": 25.296000003814697
        },
        {
            "fragment": "5{8{13,25,27,29}17}",
            "time": 25.296000003814697
        },
        {
            "fragment": "1{2,3{5{8{13,25,27,29}17}}21}",
            "time": 25.296000003814697
        },
        {
            "fragment": "1{2,3{5{8{11,22,27,28}17}}21}",
            "time": 26.246000051498413
        },
        {
            "fragment": "1{2,3{5{8{11,22,27,28}17}}21}",
            "time": 26.246000051498413
        },
        {
            "fragment": "8{13,25,27,29}",
            "time": 26.302000045776367
        },
        {
            "fragment": "27,",
            "time": 26.302000045776367
        },
        {
            "fragment": "28,",
            "time": 26.302000045776367
        },
        {
            "fragment": "2,",
            "time": 26.352999925613403
        },
        {
            "fragment": "3{5{8{13,25,27,29}17}}",
            "time": 26.352999925613403
        },
        {
            "fragment": "3{5{8{13,25,27,29}17}}",
            "time": 26.352999925613403
        },
        {
            "fragment": "21,",
            "time": 26.352999925613403
        },
        {
            "fragment": "1{2,3{5{8{11,22,27,28}17}}21}",
            "time": 26.438999891281128
        },
        {
            "fragment": "1{2,3{5{8{11,22,27,28}17}}21}",
            "time": 26.438999891281128
        },
        {
            "fragment": "8{13,25,27,29}",
            "time": 30.07200002670288
        },
        {
            "fragment": "17,",
            "time": 30.07200002670288
        },
        {
            "fragment": "3{5{8{11,22,27,28}17}}",
            "time": 30.151000022888184
        },
        {
            "fragment": "1{2,3{5{8{11,22,27,28}17}}21}",
            "time": 30.151000022888184
        },
        {
            "fragment": "8{13,25,27,29}",
            "time": 30.221999883651733
        },
        {
            "fragment": "3{5{8{11,22,27,28}17}}",
            "time": 30.221999883651733
        },
        {
            "fragment": "3{5{8{13,25,27,29}17}}",
            "time": 30.27900004386902
        },
        {
            "fragment": "27,",
            "time": 30.27900004386902
        },
        {
            "fragment": "13,",
            "time": 30.27900004386902
        },
        {
            "fragment": "28,",
            "time": 30.27900004386902
        },
        {
            "fragment": "17,",
            "time": 30.27900004386902
        },
        {
            "fragment": "2,",
            "time": 31.07800006866455
        },
        {
            "fragment": "5{8{13,25,27,29}17}",
            "time": 31.07800006866455
        },
        {
            "fragment": "3{5{8{13,25,27,29}17}}",
            "time": 31.07800006866455
        },
        {
            "fragment": "17,",
            "time": 31.07800006866455
        },
        {
            "fragment": "8{13,25,27,29}",
            "time": 31.07800006866455
        },
        {
            "fragment": "1{2,3{5{8{13,25,27,29}17}}21}",
            "time": 31.191999912261963
        },
        {
            "fragment": "1{2,3{5{8{13,25,27,29}17}}21}",
            "time": 35.23699998855591
        },
        {
            "fragment": "28,",
            "time": 35.23699998855591
        },
        {
            "fragment": "1{2,3{5{8{11,25,26,28}18}}21}",
            "time": 39.026999950408936
        },
        {
            "fragment": "25,",
            "time": 39.621999979019165
        },
        {
            "fragment": "29,",
            "time": 39.621999979019165
        },
        {
            "fragment": "21,",
            "time": 39.621999979019165
        },
        {
            "fragment": "2,",
            "time": 39.70300006866455
        },
        {
            "fragment": "13,",
            "time": 39.70300006866455
        },
        {
            "fragment": "25,",
            "time": 39.70300006866455
        },
        {
            "fragment": "26,",
            "time": 39.70300006866455
        },
        {
            "fragment": "5{8{11,25,26,28}18}",
            "time": 39.78200006484985
        },
        {
            "fragment": "7{18,8{15,22,26,29}}",
            "time": 95.18700003623962
        },
        {
            "fragment": "3{7{18,8{15,22,26,29}}}",
            "time": 95.75699996948242
        },
        {
            "fragment": "4{5{8{12,25,26,28}20{19}}3{7{18,8{15,22,26,29}}}}",
            "time": 95.79900002479553
        },
        {
            "fragment": "2,",
            "time": 97.01900005340576
        },
        {
            "fragment": "8{12,25,26,28}",
            "time": 97.01900005340576
        },
        {
            "fragment": "1{2,4{5{8{12,25,26,28}20{19}}3{7{18,8{15,22,26,29}}}}21}",
            "time": 97.14299988746643
        },
        {
            "fragment": "2,",
            "time": 97.25
        },
        {
            "fragment": "3{7{18,8{15,22,26,29}}}",
            "time": 97.25
        },
        {
            "fragment": "22,",
            "time": 97.25
        },
        {
            "fragment": "18,",
            "time": 99.23099994659424
        },
        {
            "fragment": "2,",
            "time": 99.84400010108948
        },
        {
            "fragment": "3{7{18,8{15,22,26,29}}}",
            "time": 99.84400010108948
        },
        {
            "fragment": "3{7{18,8{15,22,26,29}}}",
            "time": 99.8970000743866
        },
        {
            "fragment": "1{2,4{5{8{12,25,26,28}20{19}}3{7{18,8{15,22,26,29}}}}21}",
            "time": 99.94000005722046
        },
        {
            "fragment": "7{18,8{15,22,26,29}}",
            "time": 101.16300010681152
        },
        {
            "fragment": "7{18,8{15,22,26,29}}",
            "time": 101.25
        },
        {
            "fragment": "2,",
            "time": 101.27099990844727
        },
        {
            "fragment": "3{7{18,8{15,22,26,29}}}",
            "time": 101.27099990844727
        },
        {
            "fragment": "2,",
            "time": 102.00300002098083
        },
        {
            "fragment": "3{7{18,8{15,22,26,29}}}",
            "time": 102.00300002098083
        },
        {
            "fragment": "1{2,4{5{8{12,25,26,28}20{19}}3{7{18,8{15,22,26,29}}}}21}",
            "time": 102.00300002098083
        },
        {
            "fragment": "2,",
            "time": 102.00300002098083
        },
        {
            "fragment": "15,",
            "time": 102.00300002098083
        },
        {
            "fragment": "21,",
            "time": 102.00300002098083
        },
        {
            "fragment": "8{12,25,26,28}",
            "time": 102.0569999217987
        },
        {
            "fragment": "1{2,4{5{8{12,25,26,28}20{19}}3{7{18,8{15,22,26,29}}}}21}",
            "time": 102.11100006103516
        },
        {
            "fragment": "1{2,4{5{8{12,25,26,28}20{19}}3{7{18,8{15,22,26,29}}}}21}",
            "time": 102.11100006103516
        },
        {
            "fragment": "2,",
            "time": 102.19799995422363
        },
        {
            "fragment": "7{18,8{15,22,26,29}}",
            "time": 102.19799995422363
        },
        {
            "fragment": "21,",
            "time": 102.19799995422363
        },
        {
            "fragment": "15,",
            "time": 102.19799995422363
        },
        {
            "fragment": "22,",
            "time": 102.19799995422363
        },
        {
            "fragment": "26,",
            "time": 102.19799995422363
        },
        {
            "fragment": "19,",
            "time": 102.19799995422363
        },
        {
            "fragment": "1{2,4{5{8{12,25,26,28}20{19}}3{7{18,8{15,22,26,29}}}}21}",
            "time": 102.25099992752075
        },
        {
            "fragment": "2,",
            "time": 102.34800004959106
        },
        {
            "fragment": "22,",
            "time": 102.34800004959106
        },
        {
            "fragment": "28,",
            "time": 102.34800004959106
        },
        {
            "fragment": "7{18,8{15,22,26,29}}",
            "time": 102.40400004386902
        },
        {
            "fragment": "18,",
            "time": 102.40400004386902
        },
        {
            "fragment": "25,",
            "time": 102.40400004386902
        },
        {
            "fragment": "29,",
            "time": 102.40400004386902
        },
        {
            "fragment": "3{7{18,8{15,22,26,29}}}",
            "time": 102.40400004386902
        },
        {
            "fragment": "7{18,8{15,22,26,29}}",
            "time": 102.49799990653992
        },
        {
            "fragment": "21,",
            "time": 102.49799990653992
        },
        {
            "fragment": "2,",
            "time": 102.53900003433228
        }
    ],
    "experiment_description": "Fragments usage and modification probability - In this experiment, the probability of using fragments and the probability of modifiying fragments are changed.",
    "iterations": [
        {
            "final_grammar": "1: Program = begin\n    state = Init\n    Blocks\n    End\nend\n2: Init = mc_init(start_pos)\n3: Blocks = Block\n4: Blocks = begin\n    Block\n    Blocks\nend\n5: Block = while true\n    Move\n    Bool || break\nend\n6: Block = Move\n7: Block = if Bool\n    Move\nend\n8: Move = mc_move!(state, Direction, Times, Sprint, Jump)\n9: Direction = [\"forward\"]\n10: Direction = [\"back\"]\n11: Direction = [\"left\"]\n12: Direction = [\"right\"]\n13: Direction = [\"forward\", \"left\"]\n14: Direction = [\"forward\", \"right\"]\n15: Direction = [\"back\", \"left\"]\n16: Direction = [\"back\", \"right\"]\n17: Bool = mc_was_good_move(state)\n18: Bool = mc_has_moved(state)\n19: Bool = mc_is_done(state)\n20: Bool = !Bool\n21: End = mc_end(state)\n22: Times = 1\n23: Times = 2\n24: Times = 3\n25: Times = 4\n26: Sprint = true\n27: Sprint = false\n28: Jump = true\n29: Jump = false\n",
            "initial_position": [
                169.5,
                71.0,
                234.5
            ],
            "iterations": 83,
            "runtime": 42.68499994277954
        },
        {
            "final_grammar": "1: Program = begin\n    state = Init\n    Blocks\n    End\nend\n2: Init = mc_init(start_pos)\n3: Blocks = Block\n4: Blocks = begin\n    Block\n    Blocks\nend\n5: Block = while true\n    Move\n    Bool || break\nend\n6: Block = Move\n7: Block = if Bool\n    Move\nend\n8: Move = mc_move!(state, Direction, Times, Sprint, Jump)\n9: Direction = [\"forward\"]\n10: Direction = [\"back\"]\n11: Direction = [\"left\"]\n12: Direction = [\"right\"]\n13: Direction = [\"forward\", \"left\"]\n14: Direction = [\"forward\", \"right\"]\n15: Direction = [\"back\", \"left\"]\n16: Direction = [\"back\", \"right\"]\n17: Bool = mc_was_good_move(state)\n18: Bool = mc_has_moved(state)\n19: Bool = mc_is_done(state)\n20: Bool = !Bool\n21: End = mc_end(state)\n22: Times = 1\n23: Times = 2\n24: Times = 3\n25: Times = 4\n26: Sprint = true\n27: Sprint = false\n28: Jump = true\n29: Jump = false\n",
            "initial_position": [
                189.69999998807907,
                69.0,
                251.69999998807907
            ],
            "iterations": 75,
            "runtime": 22.628000020980835
        },
        {
            "final_grammar": "1: Program = begin\n    state = Init\n    Blocks\n    End\nend\n2: Init = mc_init(start_pos)\n3: Blocks = Block\n4: Blocks = begin\n    Block\n    Blocks\nend\n5: Block = while true\n    Move\n    Bool || break\nend\n6: Block = Move\n7: Block = if Bool\n    Move\nend\n8: Move = mc_move!(state, Direction, Times, Sprint, Jump)\n9: Direction = [\"forward\"]\n10: Direction = [\"back\"]\n11: Direction = [\"left\"]\n12: Direction = [\"right\"]\n13: Direction = [\"forward\", \"left\"]\n14: Direction = [\"forward\", \"right\"]\n15: Direction = [\"back\", \"left\"]\n16: Direction = [\"back\", \"right\"]\n17: Bool = mc_was_good_move(state)\n18: Bool = mc_has_moved(state)\n19: Bool = mc_is_done(state)\n20: Bool = !Bool\n21: End = mc_end(state)\n22: Times = 1\n23: Times = 2\n24: Times = 3\n25: Times = 4\n26: Sprint = true\n27: Sprint = false\n28: Jump = true\n29: Jump = false\n",
            "initial_position": [
                218.26445875745193,
                67.0,
                291.04277229540037
            ],
            "iterations": 29,
            "runtime": 41.87000012397766
        }
    ],
    "specification_config": {
        "max_reward": 74.0,
        "reward_percentages": [
            0.1,
            0.2,
            0.3,
            0.4,
            0.5,
            0.6,
            0.7,
            0.8,
            0.9
        ],
        "require_done": false
    },
    "world_description": "Relatively flat. Some trees. Small cave opening.",
    "generated_programs": [
        {
            "time": 0.0009999275207519531,
            "program": "1{2,4{7{19,8{10,24,27,28}}3{6{8{14,22,26,28}}}}21}"
        },
        {
            "time": 0.08599996566772461,
            "program": "1{2,3{6{8{16,25,26,29}}}21}"
        },
        {
            "time": 0.1700000762939453,
            "program": "1{2,4{7{20{19}8{9,25,27,28}}3{6{8{11,23,27,29}}}}21}"
        },
        {
            "time": 0.2720000743865967,
            "program": "1{2,3{5{8{14,24,26,28}19}}21}"
        },
        {
            "time": 0.34400010108947754,
            "program": "1{2,3{5{8{11,24,26,29}17}}21}"
        },
        {
            "time": 2.319999933242798,
            "program": "1{2,3{6{8{12,24,26,29}}}21}"
        },
        {
            "time": 2.4240000247955322,
            "program": "1{2,3{5{8{9,24,26,29}17}}21}"
        },
        {
            "time": 3.1570000648498535,
            "program": "1{2,4{7{20{17}8{11,24,26,29}}3{7{18,8{15,25,27,28}}}}21}"
        },
        {
            "time": 3.2769999504089355,
            "program": "1{2,4{7{19,8{11,24,26,29}}3{6{8{13,23,27,29}}}}21}"
        },
        {
            "time": 3.3389999866485596,
            "program": "1{2,3{5{8{11,24,26,29}hole[Bool[0, 0, 0, 0, 0, 0, 0, 0, 0, 0, 0, 0, 0, 0, 0, 0, 1, 1, 1, 1, 0, 0, 0, 0, 0, 0, 0, 0, 0, 0, 1, 0, 0, 0, 0, 0, 0, 0, 0, 0, 0, 0, 0, 0, 0, 0, 0, 0, 0, 0, 0, 0]]}}21}"
        },
        {
            "time": 6.691999912261963,
            "program": "1{2,3{6{8{11,24,26,29}}}21}"
        },
        {
            "time": 6.759000062942505,
            "program": "1{2,3{6{8{12,25,27,29}}}21}"
        },
        {
            "time": 6.835999965667725,
            "program": "1{2,3{6{8{9,25,27,29}}}21}"
        },
        {
            "time": 6.915999889373779,
            "program": "1{2,4{7{hole[Bool[0, 0, 0, 0, 0, 0, 0, 0, 0, 0, 0, 0, 0, 0, 0, 0, 1, 1, 1, 1, 0, 0, 0, 0, 0, 0, 0, 0, 0, 0, 1, 0, 0, 0, 0, 0, 0, 0, 0, 0, 0, 0, 0, 0, 0, 0, 0, 0, 0, 0, 0, 0]],8{11,25,27,28}}3{6{8{16,22,27,29}}}}21}"
        },
        {
            "time": 7.901000022888184,
            "program": "1{2,4{5{8{11,24,26,29}17}3{5{8{11,24,26,29}17}}}21}"
        },
        {
            "time": 9.865999937057495,
            "program": "1{2,3{5{8{15,24,26,28}19}}21}"
        },
        {
            "time": 9.971999883651733,
            "program": "1{2,3{6{8{16,24,26,29}}}21}"
        },
        {
            "time": 10.039999961853027,
            "program": "1{2,4{7{hole[Bool[0, 0, 0, 0, 0, 0, 0, 0, 0, 0, 0, 0, 0, 0, 0, 0, 1, 1, 1, 1, 0, 0, 0, 0, 0, 0, 0, 0, 0, 0, 1, 0, 0, 0, 0, 0, 0, 0, 0, 0, 0, 0, 0, 0, 0, 0, 0, 0, 0, 0, 0, 0]],8{14,24,26,29}}3{6{8{10,22,27,29}}}}21}"
        },
        {
            "time": 10.990000009536743,
            "program": "1{2,3{6{8{10,22,27,28}}}21}"
        },
        {
            "time": 11.04800009727478,
            "program": "1{2,3{6{8{11,23,26,28}}}21}"
        },
        {
            "time": 11.118000030517578,
            "program": "1{2,3{7{17,8{11,24,26,29}}}21}"
        },
        {
            "time": 11.158999919891357,
            "program": "1{2,4{5{8{10,25,26,29}hole[Bool[0, 0, 0, 0, 0, 0, 0, 0, 0, 0, 0, 0, 0, 0, 0, 0, 1, 1, 1, 1, 0, 0, 0, 0, 0, 0, 0, 0, 0, 0, 1, 0, 0, 0, 0, 0, 0, 0, 0, 0, 0, 0, 0, 0, 0, 0, 0, 0, 0, 0, 0, 0]]}3{6{8{11,24,26,29}}}}21}"
        },
        {
            "time": 16.000999927520752,
            "program": "1{2,4{5{8{13,25,27,29}19}3{5{8{12,25,26,29}18}}}21}"
        },
        {
            "time": 16.944999933242798,
            "program": "1{2,4{6{8{14,22,27,28}}3{6{8{11,23,26,29}}}}21}"
        },
        {
            "time": 17.03500008583069,
            "program": "1{2,3{6{8{13,23,26,29}}}21}"
        },
        {
            "time": 17.094000101089478,
            "program": "1{2,3{6{8{10,22,26,29}}}21}"
        },
        {
            "time": 17.141000032424927,
            "program": "1{2,3{5{8{11,22,27,29}20{18}}}21}"
        },
        {
            "time": 17.191999912261963,
            "program": "1{2,3{5{8{11,23,26,28}hole[Bool[0, 0, 0, 0, 0, 0, 0, 0, 0, 0, 0, 0, 0, 0, 0, 0, 1, 1, 1, 1, 0, 0, 0, 0, 0, 0, 0, 0, 0, 0, 1, 0, 0, 0, 0, 0, 0, 0, 0, 0, 0, 0, 0, 0, 0, 0, 0, 0, 0, 0, 0, 0]]}}21}"
        },
        {
            "time": 19.749000072479248,
            "program": "1{2,3{6{8{11,24,27,29}}}21}"
        },
        {
            "time": 19.818000078201294,
            "program": "1{2,3{5{8{11,24,27,28}17}}21}"
        },
        {
            "time": 21.947999954223633,
            "program": "1{2,3{7{19,8{16,24,26,28}}}21}"
        },
        {
            "time": 22.009999990463257,
            "program": "1{2,3{5{8{12,24,27,29}17}}21}"
        },
        {
            "time": 22.09599995613098,
            "program": "1{2,3{7{17,8{14,24,27,28}}}21}"
        },
        {
            "time": 22.138999938964844,
            "program": "1{2,3{6{8{12,23,26,29}}}21}"
        },
        {
            "time": 22.180999994277954,
            "program": "1{2,3{5{8{13,24,26,28}19}}21}"
        },
        {
            "time": 22.252000093460083,
            "program": "1{2,3{5{8{13,25,27,29}17}}21}"
        },
        {
            "time": 24.48099994659424,
            "program": "1{2,3{5{8{14,23,26,29}17}}21}"
        },
        {
            "time": 25.07200002670288,
            "program": "1{2,3{6{8{13,25,27,29}}}21}"
        },
        {
            "time": 25.177000045776367,
            "program": "1{2,3{5{8{15,25,27,29}17}}21}"
        },
        {
            "time": 25.253999948501587,
            "program": "1{2,3{7{19,8{13,23,27,28}}}21}"
        },
        {
            "time": 25.296000003814697,
            "program": "1{2,3{5{8{11,22,27,28}17}}21}"
        },
        {
            "time": 26.246999979019165,
            "program": "1{2,3{7{19,8{14,22,27,29}}}21}"
        },
        {
            "time": 26.302000045776367,
            "program": "1{2,3{5{8{15,24,27,28}17}}21}"
        },
        {
            "time": 26.352999925613403,
            "program": "1{2,3{5{8{15,25,27,28}17}}21}"
        },
        {
            "time": 26.438999891281128,
            "program": "1{2,3{5{8{9,25,26,29}20{19}}}21}"
        },
        {
            "time": 30.07200002670288,
            "program": "1{2,3{5{8{13,25,27,29}20{17}}}21}"
        },
        {
            "time": 30.151000022888184,
            "program": "1{2,4{7{19,8{10,23,27,29}}3{6{8{12,24,27,29}}}}21}"
        },
        {
            "time": 30.221999883651733,
            "program": "1{2,4{6{8{13,23,27,29}}3{7{20{18}8{15,25,26,29}}}}21}"
        },
        {
            "time": 30.27900004386902,
            "program": "1{2,4{6{8{9,24,27,29}}3{5{8{13,22,26,28}17}}}21}"
        },
        {
            "time": 31.07800006866455,
            "program": "1{2,4{6{8{10,23,26,29}}3{7{20{17}8{13,25,27,28}}}}21}"
        },
        {
            "time": 31.191999912261963,
            "program": "1{2,3{5{8{13,25,27,29}hole[Bool[0, 0, 0, 0, 0, 0, 0, 0, 0, 0, 0, 0, 0, 0, 0, 0, 1, 1, 1, 1, 0, 0, 0, 0, 0, 0, 0, 0, 0, 0, 1, 0, 0, 0, 0, 0, 0, 0, 0, 0, 0, 0, 0, 0, 0, 0, 0, 0, 0, 0, 0, 0, 0, 0, 0, 0, 0, 0, 0]]}}21}"
        },
        {
            "time": 35.23699998855591,
            "program": "1{2,3{5{8{11,25,26,28}18}}21}"
        },
        {
            "time": 39.02799987792969,
            "program": "1{2,3{7{hole[Bool[0, 0, 0, 0, 0, 0, 0, 0, 0, 0, 0, 0, 0, 0, 0, 0, 1, 1, 1, 1, 0, 0, 0, 0, 0, 0, 0, 0, 0, 0, 1, 0, 0, 0, 0, 0, 0, 0, 0, 0, 0, 0, 0, 0, 0, 0, 0, 0, 0, 0, 0, 0, 0, 0, 0, 0, 0, 0, 0, 0]],8{14,22,26,28}}}21}"
        },
        {
            "time": 39.621999979019165,
            "program": "1{2,3{6{8{14,25,27,29}}}21}"
        },
        {
            "time": 39.70300006866455,
            "program": "1{2,3{6{8{13,25,26,28}}}21}"
        },
        {
            "time": 39.78200006484985,
            "program": "1{2,3{5{8{16,25,27,28}18}}21}"
        },
        {
            "time": 42.68499994277954,
            "program": "1{2,4{6{8{10,24,26,29}}3{6{8{16,24,26,28}}}}21}"
        },
        {
            "time": 42.76099991798401,
            "program": "1{2,3{5{8{9,22,26,28}19}}21}"
        },
        {
            "time": 42.80800008773804,
            "program": "1{2,3{7{19,8{15,25,26,29}}}21}"
        },
        {
            "time": 42.835999965667725,
            "program": "1{2,3{5{8{9,23,26,28}19}}21}"
        },
        {
            "time": 42.875,
            "program": "1{2,3{6{8{11,25,26,29}}}21}"
        },
        {
            "time": 42.95099997520447,
            "program": "1{2,4{5{8{12,24,27,28}19}3{6{8{13,25,26,28}}}}21}"
        },
        {
            "time": 43.04800009727478,
            "program": "1{2,3{6{8{11,24,26,29}}}21}"
        },
        {
            "time": 43.125,
            "program": "1{2,3{6{8{16,22,27,28}}}21}"
        },
        {
            "time": 43.15499997138977,
            "program": "1{2,4{6{8{14,25,27,29}}3{6{8{11,24,26,28}}}}21}"
        },
        {
            "time": 43.25999999046326,
            "program": "1{2,3{7{17,8{10,22,27,29}}}21}"
        },
        {
            "time": 43.300999879837036,
            "program": "1{2,3{6{8{12,24,27,28}}}21}"
        },
        {
            "time": 43.348999977111816,
            "program": "1{2,3{5{8{14,22,27,28}19}}21}"
        },
        {
            "time": 43.401999950408936,
            "program": "1{2,3{7{18,8{10,22,26,29}}}21}"
        },
        {
            "time": 43.44600009918213,
            "program": "1{2,3{5{8{13,22,26,28}19}}21}"
        },
        {
            "time": 43.47499990463257,
            "program": "1{2,4{6{8{14,23,26,28}}3{6{8{16,22,27,28}}}}21}"
        },
        {
            "time": 43.54299998283386,
            "program": "1{2,3{6{8{15,22,26,28}}}21}"
        },
        {
            "time": 43.592000007629395,
            "program": "1{2,4{6{8{13,24,26,29}}3{5{8{11,24,26,28}19}}}21}"
        },
        {
            "time": 43.700000047683716,
            "program": "1{2,3{6{8{9,22,27,28}}}21}"
        },
        {
            "time": 43.74900007247925,
            "program": "1{2,3{6{8{16,23,26,28}}}21}"
        },
        {
            "time": 43.799999952316284,
            "program": "1{2,4{6{8{16,23,26,28}}3{6{8{9,23,27,29}}}}21}"
        },
        {
            "time": 43.888999938964844,
            "program": "1{2,3{6{8{14,25,27,28}}}21}"
        },
        {
            "time": 43.97699999809265,
            "program": "1{2,3{6{8{14,23,27,28}}}21}"
        },
        {
            "time": 44.039000034332275,
            "program": "1{2,3{6{8{10,24,27,29}}}21}"
        },
        {
            "time": 44.111000061035156,
            "program": "1{2,3{7{18,8{16,24,27,29}}}21}"
        },
        {
            "time": 44.15000009536743,
            "program": "1{2,3{6{8{10,22,27,28}}}21}"
        },
        {
            "time": 44.17899990081787,
            "program": "1{2,3{7{18,8{9,25,26,29}}}21}"
        },
        {
            "time": 44.21799993515015,
            "program": "1{2,3{6{8{15,23,27,29}}}21}"
        },
        {
            "time": 44.25600004196167,
            "program": "1{2,3{6{8{13,23,26,28}}}21}"
        },
        {
            "time": 44.31399989128113,
            "program": "1{2,3{6{8{13,22,27,29}}}21}"
        },
        {
            "time": 44.36299991607666,
            "program": "1{2,3{5{8{16,24,27,28}19}}21}"
        },
        {
            "time": 44.41100001335144,
            "program": "1{2,3{5{8{14,25,27,29}19}}21}"
        },
        {
            "time": 44.48799991607666,
            "program": "1{2,4{6{8{14,23,26,28}}3{7{19,8{13,23,26,28}}}}21}"
        },
        {
            "time": 44.545000076293945,
            "program": "1{2,3{5{8{10,25,27,28}19}}21}"
        },
        {
            "time": 44.62599992752075,
            "program": "1{2,3{6{8{12,24,26,29}}}21}"
        },
        {
            "time": 44.693000078201294,
            "program": "1{2,4{6{8{14,25,26,28}}3{6{8{12,23,26,28}}}}21}"
        },
        {
            "time": 44.79200005531311,
            "program": "1{2,3{7{20{19}8{10,22,26,29}}}21}"
        },
        {
            "time": 44.83899998664856,
            "program": "1{2,4{5{8{11,22,26,28}hole[Bool[0, 0, 0, 0, 0, 0, 0, 0, 0, 0, 0, 0, 0, 0, 0, 0, 1, 1, 1, 1, 0, 0, 0, 0, 0, 0, 0, 0, 0, 0, 1, 0, 0, 0, 0, 0, 0, 0, 0, 0, 0]]}3{7{hole[Bool[0, 0, 0, 0, 0, 0, 0, 0, 0, 0, 0, 0, 0, 0, 0, 0, 1, 1, 1, 1, 0, 0, 0, 0, 0, 0, 0, 0, 0, 0, 1, 0, 0, 0, 0, 0, 0, 0, 0, 0, 0]],8{11,24,26,29}}}}21}"
        },
        {
            "time": 46.42300009727478,
            "program": "1{2,4{5{8{9,24,27,29}17}3{7{18,8{14,24,27,28}}}}21}"
        },
        {
            "time": 46.49900007247925,
            "program": "1{2,4{5{8{11,22,27,29}20{18}}3{5{8{13,22,27,29}18}}}21}"
        },
        {
            "time": 47.40599989891052,
            "program": "1{2,4{7{20{17}8{9,24,27,28}}3{6{8{13,24,26,29}}}}21}"
        },
        {
            "time": 47.48799991607666,
            "program": "1{2,3{7{hole[Bool[0, 0, 0, 0, 0, 0, 0, 0, 0, 0, 0, 0, 0, 0, 0, 0, 1, 1, 1, 1, 0, 0, 0, 0, 0, 0, 0, 0, 0, 0, 1, 0, 0, 0, 0, 0, 0, 0, 0, 0, 0]],8{12,23,26,28}}}21}"
        },
        {
            "time": 48.05999994277954,
            "program": "1{2,4{6{8{15,25,27,28}}3{7{19,8{15,23,26,29}}}}21}"
        },
        {
            "time": 48.13800001144409,
            "program": "1{2,3{6{8{15,22,27,28}}}21}"
        },
        {
            "time": 48.18499994277954,
            "program": "1{2,3{6{8{16,25,27,28}}}21}"
        },
        {
            "time": 48.27500009536743,
            "program": "1{2,3{5{8{11,24,26,28}20{18}}}21}"
        },
        {
            "time": 48.355000019073486,
            "program": "1{2,3{6{8{15,23,27,28}}}21}"
        },
        {
            "time": 48.41300010681152,
            "program": "1{2,3{5{8{10,22,26,29}17}}21}"
        },
        {
            "time": 48.46799993515015,
            "program": "1{2,3{5{8{12,25,26,28}19}}21}"
        },
        {
            "time": 48.54699993133545,
            "program": "1{2,3{6{8{9,25,27,29}}}21}"
        },
        {
            "time": 48.62700009346008,
            "program": "1{2,3{7{17,8{15,24,26,28}}}21}"
        },
        {
            "time": 48.645999908447266,
            "program": "1{2,3{7{19,8{9,25,27,28}}}21}"
        },
        {
            "time": 48.670000076293945,
            "program": "1{2,3{6{8{14,25,26,29}}}21}"
        },
        {
            "time": 48.73099994659424,
            "program": "1{2,3{6{8{13,24,27,29}}}21}"
        },
        {
            "time": 48.7960000038147,
            "program": "1{2,3{7{18,8{15,22,27,28}}}21}"
        },
        {
            "time": 48.81399989128113,
            "program": "1{2,3{7{17,8{9,23,27,29}}}21}"
        },
        {
            "time": 48.83299994468689,
            "program": "1{2,4{5{8{12,24,26,29}17}3{6{8{12,22,27,28}}}}21}"
        },
        {
            "time": 48.89299988746643,
            "program": "1{2,3{6{8{16,24,27,29}}}21}"
        },
        {
            "time": 48.96000003814697,
            "program": "1{2,4{6{8{15,25,27,29}}3{7{19,8{14,23,26,28}}}}21}"
        },
        {
            "time": 49.03600001335144,
            "program": "1{2,3{5{8{12,22,27,28}18}}21}"
        },
        {
            "time": 50.01200008392334,
            "program": "1{2,4{5{8{12,22,27,29}hole[Bool[0, 0, 0, 0, 0, 0, 0, 0, 0, 0, 0, 0, 0, 0, 0, 0, 1, 1, 1, 1, 0, 0, 0, 0, 0, 0, 0, 0, 0, 0, 1, 0, 0, 0, 0, 0, 0, 0, 0, 0, 0]]}3{5{8{15,23,27,29}hole[Bool[0, 0, 0, 0, 0, 0, 0, 0, 0, 0, 0, 0, 0, 0, 0, 0, 1, 1, 1, 1, 0, 0, 0, 0, 0, 0, 0, 0, 0, 0, 1, 0, 0, 0, 0, 0, 0, 0, 0, 0, 0]]}}}21}"
        },
        {
            "time": 52.31100010871887,
            "program": "1{2,3{7{19,8{9,22,27,29}}}21}"
        },
        {
            "time": 52.348000049591064,
            "program": "1{2,3{7{20{17}8{13,24,26,29}}}21}"
        },
        {
            "time": 52.39400005340576,
            "program": "1{2,3{6{8{15,24,27,28}}}21}"
        },
        {
            "time": 52.44000005722046,
            "program": "1{2,3{7{hole[Bool[0, 0, 0, 0, 0, 0, 0, 0, 0, 0, 0, 0, 0, 0, 0, 0, 1, 1, 1, 1, 0, 0, 0, 0, 0, 0, 0, 0, 0, 0, 1, 0, 0, 0, 0, 0, 0, 0, 0, 0, 0]],8{12,25,27,29}}}21}"
        },
        {
            "time": 53.14400005340576,
            "program": "1{2,3{6{8{10,25,27,28}}}21}"
        },
        {
            "time": 53.22699999809265,
            "program": "1{2,4{5{8{12,24,27,28}18}3{6{8{15,24,26,29}}}}21}"
        },
        {
            "time": 54.473999977111816,
            "program": "1{2,3{5{8{16,22,27,28}hole[Bool[0, 0, 0, 0, 0, 0, 0, 0, 0, 0, 0, 0, 0, 0, 0, 0, 1, 1, 1, 1, 0, 0, 0, 0, 0, 0, 0, 0, 0, 0, 1, 0, 0, 0, 0, 0, 0, 0, 0, 0, 0]]}}21}"
        },
        {
            "time": 56.29299998283386,
            "program": "1{2,4{7{17,8{12,24,26,28}}3{5{8{11,23,26,29}18}}}21}"
        },
        {
            "time": 56.355000019073486,
            "program": "1{2,4{5{8{15,25,27,29}hole[Bool[0, 0, 0, 0, 0, 0, 0, 0, 0, 0, 0, 0, 0, 0, 0, 0, 1, 1, 1, 1, 0, 0, 0, 0, 0, 0, 0, 0, 0, 0, 1, 0, 0, 0, 0, 0, 0, 0, 0, 0, 0]]}3{6{8{13,23,27,28}}}}21}"
        },
        {
            "time": 60.82200002670288,
            "program": "1{2,4{7{20{19}8{10,22,27,29}}3{6{8{13,24,27,28}}}}21}"
        },
        {
            "time": 60.90400004386902,
            "program": "1{2,3{7{18,8{15,22,26,28}}}21}"
        },
        {
            "time": 60.944000005722046,
            "program": "1{2,4{5{8{13,23,26,28}18}3{7{19,8{9,25,27,28}}}}21}"
        },
        {
            "time": 65.31299996376038,
            "program": "1{2,3{6{8{9,23,26,28}}}21}"
        },
        {
            "time": 65.37599992752075,
            "program": "1{2,4{5{8{12,25,26,28}hole[Bool[0, 0, 0, 0, 0, 0, 0, 0, 0, 0, 0, 0, 0, 0, 0, 0, 1, 1, 1, 1, 0, 0, 0, 0, 0, 0, 0, 0, 0, 0, 1, 0, 0, 0, 0, 0, 0, 0, 0, 0, 0]]}3{7{hole[Bool[0, 0, 0, 0, 0, 0, 0, 0, 0, 0, 0, 0, 0, 0, 0, 0, 1, 1, 1, 1, 0, 0, 0, 0, 0, 0, 0, 0, 0, 0, 1, 0, 0, 0, 0, 0, 0, 0, 0, 0, 0]],8{15,22,26,29}}}}21}"
        },
        {
            "time": 95.18700003623962,
            "program": "1{2,3{7{hole[Bool[0, 0, 0, 0, 0, 0, 0, 0, 0, 0, 0, 0, 0, 0, 0, 0, 1, 1, 1, 1, 0, 0, 0, 0, 0, 0, 0, 0, 0, 0, 1, 0, 0, 0, 0, 0, 0, 0, 0, 0, 0, 0, 0, 0, 0, 0, 0, 0, 0, 0, 0, 0, 0, 0, 0, 0, 0, 0, 0, 0]],8{15,22,26,29}}}21}"
        },
        {
            "time": 95.75699996948242,
            "program": "1{2,3{7{18,8{15,22,26,29}}}21}"
        },
        {
            "time": 95.79900002479553,
            "program": "1{2,4{5{8{12,23,26,28}20{19}}4{6{8{16,23,26,28}}3{7{17,8{9,24,26,29}}}}}21}"
        },
        {
            "time": 97.01900005340576,
            "program": "1{2,3{6{8{12,25,26,28}}}21}"
        },
        {
            "time": 97.14299988746643,
            "program": "1{2,4{6{8{10,24,26,28}}4{6{8{14,24,27,29}}3{7{20{18}8{13,25,26,29}}}}}21}"
        },
        {
            "time": 97.25,
            "program": "1{2,3{5{8{12,22,26,28}hole[Bool[0, 0, 0, 0, 0, 0, 0, 0, 0, 0, 0, 0, 0, 0, 0, 0, 1, 1, 1, 1, 0, 0, 0, 0, 0, 0, 0, 0, 0, 0, 1, 0, 0, 0, 0, 0, 0, 0, 0, 0, 0, 0, 0, 0, 0, 0, 0, 0, 0, 0, 0, 0, 0, 0, 0, 0, 0, 0, 0, 0]]}}21}"
        },
        {
            "time": 99.23099994659424,
            "program": "1{2,3{7{hole[Bool[0, 0, 0, 0, 0, 0, 0, 0, 0, 0, 0, 0, 0, 0, 0, 0, 1, 1, 1, 1, 0, 0, 0, 0, 0, 0, 0, 0, 0, 0, 1, 0, 0, 0, 0, 0, 0, 0, 0, 0, 0, 0, 0, 0, 0, 0, 0, 0, 0, 0, 0, 0, 0, 0, 0, 0, 0, 0, 0, 0]],8{9,23,26,28}}}21}"
        },
        {
            "time": 99.84400010108948,
            "program": "1{2,3{5{8{14,22,26,29}19}}21}"
        },
        {
            "time": 99.8970000743866,
            "program": "1{2,3{7{17,8{13,23,27,29}}}21}"
        },
        {
            "time": 99.94000005722046,
            "program": "1{2,4{5{8{12,25,26,28}20{19}}3{7{18,8{15,22,26,29}}}}21}"
        },
        {
            "time": 101.16300010681152,
            "program": "1{2,3{7{17,8{13,24,27,29}}}21}"
        },
        {
            "time": 101.25,
            "program": "1{2,3{7{19,8{15,23,26,28}}}21}"
        },
        {
            "time": 101.27099990844727,
            "program": "1{2,3{7{hole[Bool[0, 0, 0, 0, 0, 0, 0, 0, 0, 0, 0, 0, 0, 0, 0, 0, 1, 1, 1, 1, 0, 0, 0, 0, 0, 0, 0, 0, 0, 0, 1, 0, 0, 0, 0, 0, 0, 0, 0, 0, 0, 0, 0, 0, 0, 0, 0, 0, 0, 0, 0, 0, 0, 0, 0, 0, 0, 0, 0, 0]],8{9,25,27,28}}}21}"
        },
        {
            "time": 102.00300002098083,
            "program": "1{2,3{6{8{15,22,26,29}}}21}"
        },
        {
            "time": 102.0569999217987,
            "program": "1{2,3{6{8{12,22,27,28}}}21}"
        },
        {
            "time": 102.11100006103516,
            "program": "1{2,3{5{8{11,25,27,28}19}}21}"
        },
        {
            "time": 102.19799995422363,
            "program": "1{2,3{5{8{15,22,26,28}19}}21}"
        },
        {
            "time": 102.25099992752075,
            "program": "1{2,4{7{18,8{16,22,27,29}}3{5{8{15,25,26,28}19}}}21}"
        },
        {
            "time": 102.34800004959106,
            "program": "1{2,3{6{8{16,22,27,28}}}21}"
        },
        {
            "time": 102.40400004386902,
            "program": "1{2,4{7{18,8{16,25,27,29}}4{7{20{18}8{14,25,27,29}}3{7{18,8{15,22,26,29}}}}}21}"
        },
        {
            "time": 102.49799990653992,
            "program": "1{2,3{7{20{20{18}}8{15,24,26,28}}}21}"
        },
        {
            "time": 102.53900003433228,
            "program": "1{2,3{5{8{14,25,27,29}hole[Bool[0, 0, 0, 0, 0, 0, 0, 0, 0, 0, 0, 0, 0, 0, 0, 0, 1, 1, 1, 1, 0, 0, 0, 0, 0, 0, 0, 0, 0, 0, 1, 0, 0, 0, 0, 0, 0, 0, 0, 0, 0, 0, 0, 0, 0, 0, 0, 0, 0, 0, 0, 0, 0, 0, 0, 0, 0, 0, 0, 0, 0, 0, 0, 0, 0, 0, 0, 0, 0, 0, 0]]}}21}"
        }
    ],
    "try_index": 1,
    "runtime": 107.18300008773804,
    "mined_fragments": [
        {
            "fragments": "RuleNode[29,, 1{2,3{5{8{11,24,26,29}17}}21}, 5{8{11,24,26,29}17}, 3{5{8{11,24,26,29}17}}, 24,, 17,, 8{11,24,26,29}, 21,, 2,, 11,, 26,]",
            "time": 2.319999933242798
        },
        {
            "fragments": "RuleNode[29,, 25,, 5{8{13,25,27,29}17}, 3{5{8{13,25,27,29}17}}, 17,, 13,, 21,, 2,, 27,, 8{13,25,27,29}, 1{2,3{5{8{13,25,27,29}17}}21}]",
            "time": 24.480000019073486
        },
        {
            "fragments": "RuleNode[5{8{13,25,27,29}17}, 3{5{8{13,25,27,29}17}}, 28,, 17,, 22,, 11,, 8{13,25,27,29}, 1{2,3{5{8{11,22,27,28}17}}21}, 8{11,22,27,28}, 29,, 25,, 13,, 21,, 2,, 27,, 1{2,3{5{8{13,25,27,29}17}}21}, 5{8{11,22,27,28}17}, 3{5{8{11,22,27,28}17}}]",
            "time": 26.246000051498413
        },
        {
            "fragments": "RuleNode[5{8{13,25,27,29}17}, 8{11,25,26,28}, 3{5{8{13,25,27,29}17}}, 28,, 17,, 11,, 8{13,25,27,29}, 5{8{11,25,26,28}18}, 3{5{8{11,25,26,28}18}}, 29,, 25,, 13,, 21,, 2,, 27,, 18,, 26,, 1{2,3{5{8{11,25,26,28}18}}21}, 1{2,3{5{8{13,25,27,29}17}}21}]",
            "time": 39.026999950408936
        },
        {
            "fragments": "RuleNode[1{2,4{5{8{12,25,26,28}20{19}}3{7{18,8{15,22,26,29}}}}21}, 8{15,22,26,29}, 29,, 25,, 20{19}, 12,, 28,, 7{18,8{15,22,26,29}}, 8{12,25,26,28}, 3{7{18,8{15,22,26,29}}}, 4{5{8{12,25,26,28}20{19}}3{7{18,8{15,22,26,29}}}}, 19,, 22,, 5{8{12,25,26,28}20{19}}, 15,, 2,, 21,, 18,, 26,]",
            "time": 95.18700003623962
        },
        {
            "fragments": "RuleNode[16,, 8{15,22,26,29}, 20{19}, 12,, 28,, 8{16,25,27,29}, 8{12,25,26,28}, 4{5{8{12,25,26,28}20{19}}3{7{18,8{15,22,26,29}}}}, 22,, 19,, 14,, 4{7{18,8{16,25,27,29}}4{7{20{18}8{14,25,27,29}}3{7{18,8{15,22,26,29}}}}}, 1{2,4{5{8{12,25,26,28}20{19}}3{7{18,8{15,22,26,29}}}}21}, 29,, 25,, 8{14,25,27,29}, 7{18,8{15,22,26,29}}, 3{7{18,8{15,22,26,29}}}, 1{2,4{7{18,8{16,25,27,29}}4{7{20{18}8{14,25,27,29}}3{7{18,8{15,22,26,29}}}}}21}, 20{18}, 4{7{20{18}8{14,25,27,29}}3{7{18,8{15,22,26,29}}}}, 7{20{18}8{14,25,27,29}}, 15,, 21,, 2,, 7{18,8{16,25,27,29}}, 18,, 27,, 26,, 5{8{12,25,26,28}20{19}}]",
            "time": 102.49699997901917
        }
    ],
    "grammar": "1: Program = begin\n    state = Init\n    Blocks\n    End\nend\n2: Init = mc_init(start_pos)\n3: Blocks = Block\n4: Blocks = begin\n    Block\n    Blocks\nend\n5: Block = while true\n    Move\n    Bool || break\nend\n6: Block = Move\n7: Block = if Bool\n    Move\nend\n8: Move = mc_move!(state, Direction, Times, Sprint, Jump)\n9: Direction = [\"forward\"]\n10: Direction = [\"back\"]\n11: Direction = [\"left\"]\n12: Direction = [\"right\"]\n13: Direction = [\"forward\", \"left\"]\n14: Direction = [\"forward\", \"right\"]\n15: Direction = [\"back\", \"left\"]\n16: Direction = [\"back\", \"right\"]\n17: Bool = mc_was_good_move(state)\n18: Bool = mc_has_moved(state)\n19: Bool = mc_is_done(state)\n20: Bool = !Bool\n21: End = mc_end(state)\n22: Times = 1\n23: Times = 2\n24: Times = 3\n25: Times = 4\n26: Sprint = true\n27: Sprint = false\n28: Jump = true\n29: Jump = false\n",
    "evaluated_programs": [
        {
            "time": 0.08599996566772461,
            "reward": 0.14501953125,
            "program": "1{2,4{7{19,8{10,24,27,28}}3{6{8{14,22,26,28}}}}21}"
        },
        {
            "time": 0.1700000762939453,
            "reward": -0.6304702758789062,
            "program": "1{2,3{6{8{16,25,26,29}}}21}"
        },
        {
            "time": 0.2720000743865967,
            "reward": 0.34447479248046875,
            "program": "1{2,4{7{20{19}8{9,25,27,28}}3{6{8{11,23,27,29}}}}21}"
        },
        {
            "time": 0.34400010108947754,
            "reward": 0.2902984619140625,
            "program": "1{2,3{5{8{14,24,26,28}19}}21}"
        },
        {
            "time": 2.319999933242798,
            "reward": 14.32992935180664,
            "program": "1{2,3{5{8{11,24,26,29}17}}21}"
        },
        {
            "time": 2.4240000247955322,
            "reward": -0.25490570068359375,
            "program": "1{2,3{6{8{12,24,26,29}}}21}"
        },
        {
            "time": 3.1570000648498535,
            "reward": 11.833969116210938,
            "program": "1{2,3{5{8{9,24,26,29}17}}21}"
        },
        {
            "time": 3.2769999504089355,
            "reward": 0.23736572265625,
            "program": "1{2,4{7{20{17}8{11,24,26,29}}3{7{18,8{15,25,27,28}}}}21}"
        },
        {
            "time": 3.3389999866485596,
            "reward": 0.250885009765625,
            "program": "1{2,4{7{19,8{11,24,26,29}}3{6{8{13,23,27,29}}}}21}"
        },
        {
            "time": 6.759000062942505,
            "reward": 0.2533111572265625,
            "program": "1{2,3{6{8{11,24,26,29}}}21}"
        },
        {
            "time": 6.835999965667725,
            "reward": -0.3719635009765625,
            "program": "1{2,3{6{8{12,25,27,29}}}21}"
        },
        {
            "time": 6.915999889373779,
            "reward": 0.502471923828125,
            "program": "1{2,3{6{8{9,25,27,29}}}21}"
        },
        {
            "time": 9.865999937057495,
            "reward": 14.32992935180664,
            "program": "1{2,4{5{8{11,24,26,29}17}3{5{8{11,24,26,29}17}}}21}"
        },
        {
            "time": 9.971999883651733,
            "reward": -0.12615966796875,
            "program": "1{2,3{5{8{15,24,26,28}19}}21}"
        },
        {
            "time": 10.039000034332275,
            "reward": -0.43265533447265625,
            "program": "1{2,3{6{8{16,24,26,29}}}21}"
        },
        {
            "time": 11.04800009727478,
            "reward": -0.11328887939453125,
            "program": "1{2,3{6{8{10,22,27,28}}}21}"
        },
        {
            "time": 11.117000102996826,
            "reward": 0.03713226318359375,
            "program": "1{2,3{6{8{11,23,26,28}}}21}"
        },
        {
            "time": 11.158999919891357,
            "reward": 0.0,
            "program": "1{2,3{7{17,8{11,24,26,29}}}21}"
        },
        {
            "time": 16.944999933242798,
            "reward": -10.120964050292969,
            "program": "1{2,4{5{8{13,25,27,29}19}3{5{8{12,25,26,29}18}}}21}"
        },
        {
            "time": 17.03500008583069,
            "reward": -0.022216796875,
            "program": "1{2,4{6{8{14,22,27,28}}3{6{8{11,23,26,29}}}}21}"
        },
        {
            "time": 17.094000101089478,
            "reward": 0.326141357421875,
            "program": "1{2,3{6{8{13,23,26,29}}}21}"
        },
        {
            "time": 17.141000032424927,
            "reward": -0.07871246337890625,
            "program": "1{2,3{6{8{10,22,26,29}}}21}"
        },
        {
            "time": 17.191999912261963,
            "reward": 0.05783843994140625,
            "program": "1{2,3{5{8{11,22,27,29}20{18}}}21}"
        },
        {
            "time": 19.818000078201294,
            "reward": 0.2533111572265625,
            "program": "1{2,3{6{8{11,24,27,29}}}21}"
        },
        {
            "time": 21.947999954223633,
            "reward": 14.274845123291016,
            "program": "1{2,3{5{8{11,24,27,28}17}}21}"
        },
        {
            "time": 22.009999990463257,
            "reward": 0.0,
            "program": "1{2,3{7{19,8{16,24,26,28}}}21}"
        },
        {
            "time": 22.09599995613098,
            "reward": -0.19872283935546875,
            "program": "1{2,3{5{8{12,24,27,29}17}}21}"
        },
        {
            "time": 22.138999938964844,
            "reward": 0.0,
            "program": "1{2,3{7{17,8{14,24,27,28}}}21}"
        },
        {
            "time": 22.180999994277954,
            "reward": -0.10118865966796875,
            "program": "1{2,3{6{8{12,23,26,29}}}21}"
        },
        {
            "time": 22.250999927520752,
            "reward": 0.5769729614257812,
            "program": "1{2,3{5{8{13,24,26,28}19}}21}"
        },
        {
            "time": 24.480000019073486,
            "reward": 25.529098510742188,
            "program": "1{2,3{5{8{13,25,27,29}17}}21}"
        },
        {
            "time": 25.07200002670288,
            "reward": 1.0255203247070312,
            "program": "1{2,3{5{8{14,23,26,29}17}}21}"
        },
        {
            "time": 25.177000045776367,
            "reward": 0.63031005859375,
            "program": "1{2,3{6{8{13,25,27,29}}}21}"
        },
        {
            "time": 25.253999948501587,
            "reward": -0.0987091064453125,
            "program": "1{2,3{5{8{15,25,27,29}17}}21}"
        },
        {
            "time": 25.296000003814697,
            "reward": 0.0,
            "program": "1{2,3{7{19,8{13,23,27,28}}}21}"
        },
        {
            "time": 26.246000051498413,
            "reward": 8.296257019042969,
            "program": "1{2,3{5{8{11,22,27,28}17}}21}"
        },
        {
            "time": 26.302000045776367,
            "reward": 0.0,
            "program": "1{2,3{7{19,8{14,22,27,29}}}21}"
        },
        {
            "time": 26.352999925613403,
            "reward": -0.12615966796875,
            "program": "1{2,3{5{8{15,24,27,28}17}}21}"
        },
        {
            "time": 26.438999891281128,
            "reward": -0.1570281982421875,
            "program": "1{2,3{5{8{15,25,27,28}17}}21}"
        },
        {
            "time": 30.07200002670288,
            "reward": 11.833969116210938,
            "program": "1{2,3{5{8{9,25,26,29}20{19}}}21}"
        },
        {
            "time": 30.151000022888184,
            "reward": 0.63031005859375,
            "program": "1{2,3{5{8{13,25,27,29}20{17}}}21}"
        },
        {
            "time": 30.221999883651733,
            "reward": -0.25490570068359375,
            "program": "1{2,4{7{19,8{10,23,27,29}}3{6{8{12,24,27,29}}}}21}"
        },
        {
            "time": 30.27900004386902,
            "reward": 0.250885009765625,
            "program": "1{2,4{6{8{13,23,27,29}}3{7{20{18}8{15,25,26,29}}}}21}"
        },
        {
            "time": 31.07800006866455,
            "reward": 20.57367706298828,
            "program": "1{2,4{6{8{9,24,27,29}}3{5{8{13,22,26,28}17}}}21}"
        },
        {
            "time": 31.191999912261963,
            "reward": -0.1114044189453125,
            "program": "1{2,4{6{8{10,23,26,29}}3{7{20{17}8{13,25,27,28}}}}21}"
        },
        {
            "time": 39.026000022888184,
            "reward": 11.087432861328125,
            "program": "1{2,3{5{8{11,25,26,28}18}}21}"
        },
        {
            "time": 39.70300006866455,
            "reward": 0.09340667724609375,
            "program": "1{2,3{6{8{14,25,27,29}}}21}"
        },
        {
            "time": 39.78200006484985,
            "reward": 0.7616729736328125,
            "program": "1{2,3{6{8{13,25,26,28}}}21}"
        },
        {
            "time": 40.407999992370605,
            "reward": -10.166458129882812,
            "program": "1{2,3{5{8{16,25,27,28}18}}21}"
        },
        {
            "time": 42.76099991798401,
            "reward": 25.249584197998047,
            "program": "1{2,4{6{8{10,24,26,29}}3{6{8{16,24,26,28}}}}21}"
        },
        {
            "time": 42.80800008773804,
            "reward": 25.527488708496094,
            "program": "1{2,3{5{8{9,22,26,28}19}}21}"
        },
        {
            "time": 42.835999965667725,
            "reward": 25.529098510742188,
            "program": "1{2,3{7{19,8{15,25,26,29}}}21}"
        },
        {
            "time": 42.87400007247925,
            "reward": 25.521629333496094,
            "program": "1{2,3{5{8{9,23,26,28}19}}21}"
        },
        {
            "time": 42.95099997520447,
            "reward": 25.529098510742188,
            "program": "1{2,3{6{8{11,25,26,29}}}21}"
        },
        {
            "time": 43.04800009727478,
            "reward": 25.44107437133789,
            "program": "1{2,4{5{8{12,24,27,28}19}3{6{8{13,25,26,28}}}}21}"
        },
        {
            "time": 43.125,
            "reward": 25.529098510742188,
            "program": "1{2,3{6{8{11,24,26,29}}}21}"
        },
        {
            "time": 43.15499997138977,
            "reward": 25.50667953491211,
            "program": "1{2,3{6{8{16,22,27,28}}}21}"
        },
        {
            "time": 43.25999999046326,
            "reward": 25.474346160888672,
            "program": "1{2,4{6{8{14,25,27,29}}3{6{8{11,24,26,28}}}}21}"
        },
        {
            "time": 43.29900002479553,
            "reward": 25.529098510742188,
            "program": "1{2,3{7{17,8{10,22,27,29}}}21}"
        },
        {
            "time": 43.348999977111816,
            "reward": 25.46636199951172,
            "program": "1{2,3{6{8{12,24,27,28}}}21}"
        },
        {
            "time": 43.401999950408936,
            "reward": 25.520591735839844,
            "program": "1{2,3{5{8{14,22,27,28}19}}21}"
        },
        {
            "time": 43.44600009918213,
            "reward": 25.529098510742188,
            "program": "1{2,3{7{18,8{10,22,26,29}}}21}"
        },
        {
            "time": 43.47499990463257,
            "reward": 25.52587127685547,
            "program": "1{2,3{5{8{13,22,26,28}19}}21}"
        },
        {
            "time": 43.54299998283386,
            "reward": 25.47210693359375,
            "program": "1{2,4{6{8{14,23,26,28}}3{6{8{16,22,27,28}}}}21}"
        },
        {
            "time": 43.592000007629395,
            "reward": 25.51519775390625,
            "program": "1{2,3{6{8{15,22,26,28}}}21}"
        },
        {
            "time": 43.700000047683716,
            "reward": 25.52057647705078,
            "program": "1{2,4{6{8{13,24,26,29}}3{5{8{11,24,26,28}19}}}21}"
        },
        {
            "time": 43.74900007247925,
            "reward": 25.527488708496094,
            "program": "1{2,3{6{8{9,22,27,28}}}21}"
        },
        {
            "time": 43.799999952316284,
            "reward": 25.470836639404297,
            "program": "1{2,3{6{8{16,23,26,28}}}21}"
        },
        {
            "time": 43.888999938964844,
            "reward": 25.46963882446289,
            "program": "1{2,4{6{8{16,23,26,28}}3{6{8{9,23,27,29}}}}21}"
        },
        {
            "time": 43.97699999809265,
            "reward": 25.45907211303711,
            "program": "1{2,3{6{8{14,25,27,28}}}21}"
        },
        {
            "time": 44.039000034332275,
            "reward": 25.505245208740234,
            "program": "1{2,3{6{8{14,23,27,28}}}21}"
        },
        {
            "time": 44.111000061035156,
            "reward": 25.439800262451172,
            "program": "1{2,3{6{8{10,24,27,29}}}21}"
        },
        {
            "time": 44.15000009536743,
            "reward": 25.529098510742188,
            "program": "1{2,3{7{18,8{16,24,27,29}}}21}"
        },
        {
            "time": 44.17899990081787,
            "reward": 25.508834838867188,
            "program": "1{2,3{6{8{10,22,27,28}}}21}"
        },
        {
            "time": 44.21799993515015,
            "reward": 25.529098510742188,
            "program": "1{2,3{7{18,8{9,25,26,29}}}21}"
        },
        {
            "time": 44.25600004196167,
            "reward": 25.494674682617188,
            "program": "1{2,3{6{8{15,23,27,29}}}21}"
        },
        {
            "time": 44.31399989128113,
            "reward": 25.52457046508789,
            "program": "1{2,3{6{8{13,23,26,28}}}21}"
        },
        {
            "time": 44.36299991607666,
            "reward": 25.529098510742188,
            "program": "1{2,3{6{8{13,22,27,29}}}21}"
        },
        {
            "time": 44.41100001335144,
            "reward": 25.41598129272461,
            "program": "1{2,3{5{8{16,24,27,28}19}}21}"
        },
        {
            "time": 44.48799991607666,
            "reward": 25.47248077392578,
            "program": "1{2,3{5{8{14,25,27,29}19}}21}"
        },
        {
            "time": 44.545000076293945,
            "reward": 25.505245208740234,
            "program": "1{2,4{6{8{14,23,26,28}}3{7{19,8{13,23,26,28}}}}21}"
        },
        {
            "time": 44.62599992752075,
            "reward": 25.376083374023438,
            "program": "1{2,3{5{8{10,25,27,28}19}}21}"
        },
        {
            "time": 44.693000078201294,
            "reward": 25.478919982910156,
            "program": "1{2,3{6{8{12,24,26,29}}}21}"
        },
        {
            "time": 44.79200005531311,
            "reward": 25.390731811523438,
            "program": "1{2,4{6{8{14,25,26,28}}3{6{8{12,23,26,28}}}}21}"
        },
        {
            "time": 44.83899998664856,
            "reward": 25.512062072753906,
            "program": "1{2,3{7{20{19}8{10,22,26,29}}}21}"
        },
        {
            "time": 46.49799990653992,
            "reward": 25.529098510742188,
            "program": "1{2,4{5{8{9,24,27,29}17}3{7{18,8{14,24,27,28}}}}21}"
        },
        {
            "time": 47.40599989891052,
            "reward": 25.529098510742188,
            "program": "1{2,4{5{8{11,22,27,29}20{18}}3{5{8{13,22,27,29}18}}}21}"
        },
        {
            "time": 47.48799991607666,
            "reward": 25.515239715576172,
            "program": "1{2,4{7{20{17}8{9,24,27,28}}3{6{8{13,24,26,29}}}}21}"
        },
        {
            "time": 48.13800001144409,
            "reward": 25.414966583251953,
            "program": "1{2,4{6{8{15,25,27,28}}3{7{19,8{15,23,26,29}}}}21}"
        },
        {
            "time": 48.18499994277954,
            "reward": 25.51519775390625,
            "program": "1{2,3{6{8{15,22,27,28}}}21}"
        },
        {
            "time": 48.27500009536743,
            "reward": 25.358478546142578,
            "program": "1{2,3{6{8{16,25,27,28}}}21}"
        },
        {
            "time": 48.355000019073486,
            "reward": 25.52057647705078,
            "program": "1{2,3{5{8{11,24,26,28}20{18}}}21}"
        },
        {
            "time": 48.41300010681152,
            "reward": 25.490150451660156,
            "program": "1{2,3{6{8{15,23,27,28}}}21}"
        },
        {
            "time": 48.46799993515015,
            "reward": 25.512062072753906,
            "program": "1{2,3{5{8{10,22,26,29}17}}21}"
        },
        {
            "time": 48.54699993133545,
            "reward": 25.437175750732422,
            "program": "1{2,3{5{8{12,25,26,28}19}}21}"
        },
        {
            "time": 48.62700009346008,
            "reward": 25.529098510742188,
            "program": "1{2,3{6{8{9,25,27,29}}}21}"
        },
        {
            "time": 48.645999908447266,
            "reward": 25.529098510742188,
            "program": "1{2,3{7{17,8{15,24,26,28}}}21}"
        },
        {
            "time": 48.670000076293945,
            "reward": 25.529098510742188,
            "program": "1{2,3{7{19,8{9,25,27,28}}}21}"
        },
        {
            "time": 48.73099994659424,
            "reward": 25.47248077392578,
            "program": "1{2,3{6{8{14,25,26,29}}}21}"
        },
        {
            "time": 48.795000076293945,
            "reward": 25.529098510742188,
            "program": "1{2,3{6{8{13,24,27,29}}}21}"
        },
        {
            "time": 48.81399989128113,
            "reward": 25.529098510742188,
            "program": "1{2,3{7{18,8{15,22,27,28}}}21}"
        },
        {
            "time": 48.83299994468689,
            "reward": 25.529098510742188,
            "program": "1{2,3{7{17,8{9,23,27,29}}}21}"
        },
        {
            "time": 48.89299988746643,
            "reward": 25.448970794677734,
            "program": "1{2,4{5{8{12,24,26,29}17}3{6{8{12,22,27,28}}}}21}"
        },
        {
            "time": 48.96000003814697,
            "reward": 25.42852783203125,
            "program": "1{2,3{6{8{16,24,27,29}}}21}"
        },
        {
            "time": 49.03600001335144,
            "reward": 25.428363800048828,
            "program": "1{2,4{6{8{15,25,27,29}}3{7{19,8{14,23,26,28}}}}21}"
        },
        {
            "time": 50.01200008392334,
            "reward": 18.611801147460938,
            "program": "1{2,3{5{8{12,22,27,28}18}}21}"
        },
        {
            "time": 52.348000049591064,
            "reward": 25.529098510742188,
            "program": "1{2,3{7{19,8{9,22,27,29}}}21}"
        },
        {
            "time": 52.39400005340576,
            "reward": 25.529098510742188,
            "program": "1{2,3{7{20{17}8{13,24,26,29}}}21}"
        },
        {
            "time": 52.44000005722046,
            "reward": 25.452117919921875,
            "program": "1{2,3{6{8{15,24,27,28}}}21}"
        },
        {
            "time": 53.22699999809265,
            "reward": 25.376083374023438,
            "program": "1{2,3{6{8{10,25,27,28}}}21}"
        },
        {
            "time": 54.473000049591064,
            "reward": 15.456634521484375,
            "program": "1{2,4{5{8{12,24,27,28}18}3{6{8{15,24,26,29}}}}21}"
        },
        {
            "time": 56.355000019073486,
            "reward": 25.529098510742188,
            "program": "1{2,4{7{17,8{12,24,26,28}}3{5{8{11,23,26,29}18}}}21}"
        },
        {
            "time": 60.90400004386902,
            "reward": 25.52057647705078,
            "program": "1{2,4{7{20{19}8{10,22,27,29}}3{6{8{13,24,27,28}}}}21}"
        },
        {
            "time": 60.944000005722046,
            "reward": 25.529098510742188,
            "program": "1{2,3{7{18,8{15,22,26,28}}}21}"
        },
        {
            "time": 63.092000007629395,
            "reward": 69.15917301177979,
            "program": "1{2,4{5{8{13,23,26,28}18}3{7{19,8{9,25,27,28}}}}21}"
        },
        {
            "time": 65.37599992752075,
            "reward": 69.21879768371582,
            "program": "1{2,3{6{8{9,23,26,28}}}21}"
        },
        {
            "time": 95.18700003623962,
            "reward": 59.12155723571777,
            "program": "1{2,4{5{8{12,25,26,28}20{19}}3{7{18,8{15,22,26,29}}}}21}"
        },
        {
            "time": 95.79900002479553,
            "reward": 69.19070196151733,
            "program": "1{2,3{7{18,8{15,22,26,29}}}21}"
        },
        {
            "time": 97.01900005340576,
            "reward": 59.12155723571777,
            "program": "1{2,4{5{8{12,23,26,28}20{19}}4{6{8{16,23,26,28}}3{7{17,8{9,24,26,29}}}}}21}"
        },
        {
            "time": 97.14299988746643,
            "reward": 68.94207572937012,
            "program": "1{2,3{6{8{12,25,26,28}}}21}"
        },
        {
            "time": 97.24900007247925,
            "reward": 68.4866771697998,
            "program": "1{2,4{6{8{10,24,26,28}}4{6{8{14,24,27,29}}3{7{20{18}8{13,25,26,29}}}}}21}"
        },
        {
            "time": 99.8970000743866,
            "reward": 69.31340456008911,
            "program": "1{2,3{5{8{14,22,26,29}19}}21}"
        },
        {
            "time": 99.94000005722046,
            "reward": 69.19070196151733,
            "program": "1{2,3{7{17,8{13,23,27,29}}}21}"
        },
        {
            "time": 101.16300010681152,
            "reward": 59.12155723571777,
            "program": "1{2,4{5{8{12,25,26,28}20{19}}3{7{18,8{15,22,26,29}}}}21}"
        },
        {
            "time": 101.25,
            "reward": 69.19070196151733,
            "program": "1{2,3{7{17,8{13,24,27,29}}}21}"
        },
        {
            "time": 101.27099990844727,
            "reward": 69.19070196151733,
            "program": "1{2,3{7{19,8{15,23,26,28}}}21}"
        },
        {
            "time": 102.0569999217987,
            "reward": 69.09611463546753,
            "program": "1{2,3{6{8{15,22,26,29}}}21}"
        },
        {
            "time": 102.11100006103516,
            "reward": 69.10753583908081,
            "program": "1{2,3{6{8{12,22,27,28}}}21}"
        },
        {
            "time": 102.19799995422363,
            "reward": 68.4850549697876,
            "program": "1{2,3{5{8{11,25,27,28}19}}21}"
        },
        {
            "time": 102.25099992752075,
            "reward": 68.94924449920654,
            "program": "1{2,3{5{8{15,22,26,28}19}}21}"
        },
        {
            "time": 102.34800004959106,
            "reward": 68.39882755279541,
            "program": "1{2,4{7{18,8{16,22,27,29}}3{5{8{15,25,26,28}19}}}21}"
        },
        {
            "time": 102.40400004386902,
            "reward": 69.04428195953369,
            "program": "1{2,3{6{8{16,22,27,28}}}21}"
        },
        {
            "time": 102.49699997901917,
            "reward": 69.80021142959595,
            "program": "1{2,4{7{18,8{16,25,27,29}}4{7{20{18}8{14,25,27,29}}3{7{18,8{15,22,26,29}}}}}21}"
        },
        {
            "time": 102.53900003433228,
            "reward": 69.19070196151733,
            "program": "1{2,3{7{20{20{18}}8{15,24,26,28}}}21}"
        }
    ]
}
